{
  "last_updated": "2025-11-02T01:29:40.587057",
  "total_news": 62,
  "news": [
    {
      "id": "dbba4cece12c",
      "title": "LỊCH THI ĐẤU CHUNG KẾT TỔNG – ĐẤU TRƯỜNG DANH VỌNG MÙA ĐÔNG 2025",
      "link": "https://lienquan.garena.vn/lich-thi-dau-chung-ket-tong-dau-truong-danh-vong-mua-dong-2025/",
      "summary": "<p>Chặng đường chinh phục ngôi vương Đấu Trường Danh Vọng mùa Đông 2025 đang dần đến hồi kết. Với sự góp mặt của 3 đội tuyển SGP, FPT và 1S, cái tên nào sẽ giành [&#8230;]</p>\n<p>The post <a href=\"https://lienquan.garena.vn/lich-thi-dau-chung-ket-tong-dau-truong-danh-vong-mua-dong-2025/\">LỊCH THI ĐẤU CHUNG KẾT TỔNG &#8211; ĐẤU TRƯỜNG DANH VỌNG MÙA ĐÔNG 2025</a> appeared first on <a href=\"https://lienquan.garena.vn\">Liên Quân Mobile</a>.</p>",
      "image_url": null,
      "source": "Liên Quân Mobile Official",
      "source_url": "https://lienquan.garena.vn/rss",
      "published_at": "2025-10-30T04:39:01Z",
      "crawled_at": "2025-10-30T05:01:33.891350",
      "category": "tin tức",
      "priority": 1
    },
    {
      "id": "06e6fa3b1d9d",
      "title": "HÚ HỒN VÌ LOẠT “TÁO” XỊN TỪ ĐẠI LÝ SHOPEE",
      "link": "https://lienquan.garena.vn/hu-hon-vi-loat-tao-xin-tu-dai-ly-shopee/",
      "summary": "<p>Cùng Đại lý Shopee quẩy tung đại tiệc ma quái với loạt quà tặng cực hot. Với mỗi thẻ Garena từ 20.000Đ mua tại Đại lý Shopee trên toàn quốc, cơ hội rinh về &#8220;táo&#8221; [&#8230;]</p>\n<p>The post <a href=\"https://lienquan.garena.vn/hu-hon-vi-loat-tao-xin-tu-dai-ly-shopee/\">HÚ HỒN VÌ LOẠT &#8220;TÁO&#8221; XỊN TỪ ĐẠI LÝ SHOPEE</a> appeared first on <a href=\"https://lienquan.garena.vn\">Liên Quân Mobile</a>.</p>",
      "image_url": null,
      "source": "Liên Quân Mobile Official",
      "source_url": "https://lienquan.garena.vn/rss",
      "published_at": "2025-10-29T13:00:00Z",
      "crawled_at": "2025-10-29T13:11:40.066083",
      "category": "tin tức",
      "priority": 1
    },
    {
      "id": "2a3645fbecca",
      "title": "PHÁT ĐỘNG CUỘC THI SÁNG TẠO TRANG PHỤC LIÊN QUÂN 2025",
      "link": "https://lienquan.garena.vn/phat-dong-cuoc-thi-sang-tao-trang-phuc-lien-quan-2025/",
      "summary": "<p>PHÁT ĐỘNG CUỘC THI SÁNG TẠO TRANG PHỤC LIÊN QUÂN 2025 Xin chào các Kiện tướng,  &#160; Cuộc thi sáng tạo trang phục Liên Quân năm 2025 đã chính thức quay trở lại với chủ [&#8230;]</p>\n<p>The post <a href=\"https://lienquan.garena.vn/phat-dong-cuoc-thi-sang-tao-trang-phuc-lien-quan-2025/\">PHÁT ĐỘNG CUỘC THI SÁNG TẠO TRANG PHỤC LIÊN QUÂN 2025</a> appeared first on <a href=\"https://lienquan.garena.vn\">Liên Quân Mobile</a>.</p>",
      "image_url": "https://picsum.photos/seed/https://lienquan.garena.vn/phat-dong-cuoc-thi-sang-tao-trang-phuc-lien-quan-2025//400/225",
      "source": "Liên Quân Mobile Official",
      "source_url": "https://lienquan.garena.vn/rss",
      "published_at": "2025-10-29T08:31:34Z",
      "crawled_at": "2025-10-29T09:01:35.197453",
      "category": "tướng",
      "priority": 1
    },
    {
      "id": "d12c0fc9503f",
      "title": "ĐIỀU CHỈNH GIỮA MÙA PB QUANG MINH & HẮC ÁM – 30.10.2025",
      "link": "https://lienquan.garena.vn/dieu-chinh-giua-mua-pb-quang-minh-hac-am-30-10-2025/",
      "summary": "<p>Xin chào các Kiện Tướng, Liên Quân Mobile sẽ tiến hành cập nhật không gián đoạn cho máy chủ chính thức vào ngày 30/10/2025. Trong thời gian này, người chơi có thể chủ động cập nhật vào thời [&#8230;]</p>\n<p>The post <a href=\"https://lienquan.garena.vn/dieu-chinh-giua-mua-pb-quang-minh-hac-am-30-10-2025/\">ĐIỀU CHỈNH GIỮA MÙA PB QUANG MINH &#038; HẮC ÁM &#8211; 30.10.2025</a> appeared first on <a href=\"https://lienquan.garena.vn\">Liên Quân Mobile</a>.</p>",
      "image_url": null,
      "source": "Liên Quân Mobile Official",
      "source_url": "https://lienquan.garena.vn/rss",
      "published_at": "2025-10-28T10:21:33Z",
      "crawled_at": "2025-10-28T12:01:46.244260",
      "category": "tướng",
      "priority": 1
    },
    {
      "id": "7ea0a97ce75d",
      "title": "Mở bán Eland’orr Mộng giới thần chủ",
      "link": "https://lienquan.garena.vn/mo-ban-elandorr-mong-gioi-than-chu/",
      "summary": "<p>1. Thời gian: 24.10.2025-09.11.2025 2. Bạn có thể tìm 1 lần với 18 QH hoặc 10 lần với 180 QH để săn huy hiệu thần chủ. Ngoài ra, bạn sẽ nhận 1 lượt chơi FREE [&#8230;]</p>\n<p>The post <a href=\"https://lienquan.garena.vn/mo-ban-elandorr-mong-gioi-than-chu/\">Mở bán Eland&#8217;orr Mộng giới thần chủ</a> appeared first on <a href=\"https://lienquan.garena.vn\">Liên Quân Mobile</a>.</p>",
      "image_url": null,
      "source": "Liên Quân Mobile Official",
      "source_url": "https://lienquan.garena.vn/rss",
      "published_at": "2025-10-27T04:47:35Z",
      "crawled_at": "2025-10-27T05:01:47.240868",
      "category": "tin tức",
      "priority": 1
    },
    {
      "id": "25092f9b44fe",
      "title": "Mở bán Sổ sứ mệnh 83",
      "link": "https://lienquan.garena.vn/mo-ban-so-su-menh-83/",
      "summary": "<p>Xin chào các Kiện Tướng Chào mừng đến với Sổ Sứ Mệnh mùa 83 &#8211; Cực đạo võ sĩ SỔ SỨ MỆNH MÙA 83  &#160; &#160; Các Kiện Tướng có hai lựa chọn tham gia [&#8230;]</p>\n<p>The post <a href=\"https://lienquan.garena.vn/mo-ban-so-su-menh-83/\">Mở bán Sổ sứ mệnh 83</a> appeared first on <a href=\"https://lienquan.garena.vn\">Liên Quân Mobile</a>.</p>",
      "image_url": null,
      "source": "Liên Quân Mobile Official",
      "source_url": "https://lienquan.garena.vn/rss",
      "published_at": "2025-10-27T04:44:02Z",
      "crawled_at": "2025-10-27T05:01:47.240930",
      "category": "tướng",
      "priority": 1
    },
    {
      "id": "e9ff82dce4c1",
      "title": "BẮN BI BUNG QUÀ – CHUNG SỨC NHẬN SKIN",
      "link": "https://lienquan.garena.vn/ban-bi-bung-qua-chung-suc-nhan-skin-len-toi-ss-huu-han/",
      "summary": "<p>Xin chào các Kiện tướng, Hội đồng xin gửi tới các Kiện tướng Bắn Bi Bung Quà &#8211; Chung sức nhận Skin lên tới SS Hữu hạn Bắn Bi Bung Quà &#8211; Cùng nhau nhận Rương [&#8230;]</p>\n<p>The post <a href=\"https://lienquan.garena.vn/ban-bi-bung-qua-chung-suc-nhan-skin-len-toi-ss-huu-han/\">BẮN BI BUNG QUÀ &#8211; CHUNG SỨC NHẬN SKIN</a> appeared first on <a href=\"https://lienquan.garena.vn\">Liên Quân Mobile</a>.</p>",
      "image_url": null,
      "source": "Liên Quân Mobile Official",
      "source_url": "https://lienquan.garena.vn/rss",
      "published_at": "2025-10-24T13:19:46Z",
      "crawled_at": "2025-10-24T14:01:51.700873",
      "category": "tướng",
      "priority": 1
    },
    {
      "id": "d04d22e24311",
      "title": "PHÁT ĐỘNG CUỘC THI THIẾT KẾ AVATAR LIÊN QUÂN ĐẬM CHẤT VIỆT NAM",
      "link": "https://lienquan.garena.vn/cuoc-thi-thiet-ke-avatar-lien-quan-dam-chat-viet-nam/",
      "summary": "<p>Xin chào các Kiện Tướng, Hòa chung với không khí tưng bừng mừng sinh nhật Liên Quân Mobile tròn 9 tuổi, Hội Đồng chính thức phát động một sân chơi sáng tạo mới &#8211; cuộc [&#8230;]</p>\n<p>The post <a href=\"https://lienquan.garena.vn/cuoc-thi-thiet-ke-avatar-lien-quan-dam-chat-viet-nam/\">PHÁT ĐỘNG CUỘC THI THIẾT KẾ AVATAR LIÊN QUÂN ĐẬM CHẤT VIỆT NAM</a> appeared first on <a href=\"https://lienquan.garena.vn\">Liên Quân Mobile</a>.</p>",
      "image_url": "https://picsum.photos/seed/https://lienquan.garena.vn/cuoc-thi-thiet-ke-avatar-lien-quan-dam-chat-viet-nam//400/225",
      "source": "Liên Quân Mobile Official",
      "source_url": "https://lienquan.garena.vn/rss",
      "published_at": "2025-10-24T08:30:58Z",
      "crawled_at": "2025-10-24T09:01:47.643287",
      "category": "tướng",
      "priority": 1
    },
    {
      "id": "2ccf5b1286b6",
      "title": "8 ĐỘI TUYỂN TINH HOA HỘI TỤ TẠI VÒNG CHUNG KẾT TOÀN QUỐC – TỨ PHƯƠNG ĐẠI CHIẾN MÙA ĐÔNG 2025 | AI SẼ VIẾT TIẾP LỊCH SỬ?",
      "link": "https://lienquan.garena.vn/8-doi-tuyen-tinh-hoa-hoi-tu-tai-vong-chung-ket-toan-quoc-tu-phuong-dai-chien-mua-dong-2025-ai-se-viet-tiep-lich-su/",
      "summary": "<p>Xin chào các Kiện Tướng,  Tứ Phương Đại Chiến Mùa Đông 2025 – hành trình khốc liệt nhất của cộng đồng Liên Quân đã bước vào giai đoạn quyết định: Vòng Chung Kết Toàn Quốc. [&#8230;]</p>\n<p>The post <a href=\"https://lienquan.garena.vn/8-doi-tuyen-tinh-hoa-hoi-tu-tai-vong-chung-ket-toan-quoc-tu-phuong-dai-chien-mua-dong-2025-ai-se-viet-tiep-lich-su/\">8 ĐỘI TUYỂN TINH HOA HỘI TỤ TẠI VÒNG CHUNG KẾT TOÀN QUỐC – TỨ PHƯƠNG ĐẠI CHIẾN MÙA ĐÔNG 2025 | AI SẼ VIẾT TIẾP LỊCH SỬ?</a> appeared first on <a h",
      "image_url": null,
      "source": "Liên Quân Mobile Official",
      "source_url": "https://lienquan.garena.vn/rss",
      "published_at": "2025-10-24T07:46:27Z",
      "crawled_at": "2025-10-24T08:01:48.966773",
      "category": "tướng",
      "priority": 1
    },
    {
      "id": "1edb34599c64",
      "title": "TỔNG KẾT ĐẤU TRƯỜNG DANH VỌNG MÙA ĐÔNG 2025 – PLAYOFF 1&2: CUNG ĐIỀN KINH MỸ ĐÌNH GỌI TÊN SAIGON PHANTOM, ONE STAR ESPORTS VÀ FPT X FLASH",
      "link": "https://lienquan.garena.vn/tong-ket-dau-truong-danh-vong-mua-dong-2025-playoff-12-cung-dien-kinh-my-dinh-goi-ten-saigon-phantom-one-star-esports-va-fpt-x-flash/",
      "summary": "<p>Hai trận Playoff 1 và 2 của Đấu Trường Danh Vọng Mùa Đông 2025 đã khép lại với những màn đối đầu mãn nhãn và đầy cảm xúc. Sau loạt trận căng thẳng, FPTx Flash, [&#8230;]</p>\n<p>The post <a href=\"https://lienquan.garena.vn/tong-ket-dau-truong-danh-vong-mua-dong-2025-playoff-12-cung-dien-kinh-my-dinh-goi-ten-saigon-phantom-one-star-esports-va-fpt-x-flash/\">TỔNG KẾT ĐẤU TRƯỜNG DANH VỌNG MÙA ĐÔNG 2025 – PLAYOFF 1&#038;2: CUNG ĐIỀN KINH MỸ ĐÌNH GỌI TÊN SAIGON PHANTOM, ONE STAR ESPORTS VÀ FPT X FLA",
      "image_url": null,
      "source": "Liên Quân Mobile Official",
      "source_url": "https://lienquan.garena.vn/rss",
      "published_at": "2025-10-23T12:18:34Z",
      "crawled_at": "2025-10-23T13:10:52.184208",
      "category": "esports",
      "priority": 1
    },
    {
      "id": "b9791e7d2d25",
      "title": "ĐỘI HÌNH XUẤT SẮC VÀ TỔNG KẾT BXH PLAYER OF THE MATCH GIAI ĐOẠN 2 ĐẤU TRƯỜNG DANH VỌNG MÙA ĐÔNG 2025",
      "link": "https://lienquan.garena.vn/doi-hinh-xuat-sac-va-tong-ket-bxh-player-of-the-match-giai-doan-2-dau-truong-danh-vong-mua-dong-2025/",
      "summary": "<p>Kết thúc tuần thi đấu bùng nổ và đầy cảm xúc, 4 đội tuyển mạnh nhất của ĐTDV Mùa Đông 2025 đã chính thức lộ diện. Với màn trình diễn ấn tượng, đầy bản lĩnh, [&#8230;]</p>\n<p>The post <a href=\"https://lienquan.garena.vn/doi-hinh-xuat-sac-va-tong-ket-bxh-player-of-the-match-giai-doan-2-dau-truong-danh-vong-mua-dong-2025/\">ĐỘI HÌNH XUẤT SẮC VÀ TỔNG KẾT BXH PLAYER OF THE MATCH GIAI ĐOẠN 2 ĐẤU TRƯỜNG DANH VỌNG MÙA ĐÔNG 2025</a> appeared first on <a href=\"https://lienquan.garena.vn\">Liên Quân Mobil",
      "image_url": null,
      "source": "Liên Quân Mobile Official",
      "source_url": "https://lienquan.garena.vn/rss",
      "published_at": "2025-10-22T04:26:10Z",
      "crawled_at": "2025-10-22T05:01:44.314429",
      "category": "tin tức",
      "priority": 1
    },
    {
      "id": "441fff9b818a",
      "title": "CẬP NHẬT DANH SÁCH TỈNH THÀNH MỚI TRONG GAME LIÊN QUÂN MOBILE TỪ NGÀY 22.10.2025",
      "link": "https://lienquan.garena.vn/cap-nhat-danh-sach-tinh-thanh-moi-trong-game-lien-quan-mobile-tu-ngay-22-10-2025/",
      "summary": "<p>Hệ thống Liên Quân sẽ tiến hành cập nhật danh sách tỉnh thành mới của Việt Nam kể từ phiên bản Quang Minh &#38; Hắc Ám. Thông tin chi tiết như sau: Từ ngày 22.10: [&#8230;]</p>\n<p>The post <a href=\"https://lienquan.garena.vn/cap-nhat-danh-sach-tinh-thanh-moi-trong-game-lien-quan-mobile-tu-ngay-22-10-2025/\">CẬP NHẬT DANH SÁCH TỈNH THÀNH MỚI TRONG GAME LIÊN QUÂN MOBILE TỪ NGÀY 22.10.2025</a> appeared first on <a href=\"https://lienquan.garena.vn\">Liên Quân Mobile</a>.</p>",
      "image_url": "https://picsum.photos/seed/https://lienquan.garena.vn/cap-nhat-danh-sach-tinh-thanh-moi-trong-game-lien-quan-mobile-tu-ngay-22-10-2025//400/225",
      "source": "Liên Quân Mobile Official",
      "source_url": "https://lienquan.garena.vn/rss",
      "published_at": "2025-10-21T11:39:06Z",
      "crawled_at": "2025-10-21T12:02:10.795906",
      "category": "tin tức",
      "priority": 1
    },
    {
      "id": "8b933fec791c",
      "title": "QUY TRÌNH CẬP NHẬT PHIÊN BẢN QUANG MINH & HẮC ÁM – 22.10.2025",
      "link": "https://lienquan.garena.vn/quy-trinh-cap-nhat-phien-ban-quang-minh-hac-am-22-10-2025/",
      "summary": "<p>Các Kiện Tướng thân mến, Hội đồng Liên Quân xin phép thông báo Quy trình cập nhật phiên bản mới QUANG MINH &#38; HẮC ÁM 22.10.2025 Phiên bản mới QUANG MINH &#38; HẮC ÁM sẽ được [&#8230;]</p>\n<p>The post <a href=\"https://lienquan.garena.vn/quy-trinh-cap-nhat-phien-ban-quang-minh-hac-am-22-10-2025/\">QUY TRÌNH CẬP NHẬT PHIÊN BẢN QUANG MINH &#038; HẮC ÁM – 22.10.2025</a> appeared first on <a href=\"https://lienquan.garena.vn\">Liên Quân Mobile</a>.</p>",
      "image_url": null,
      "source": "Liên Quân Mobile Official",
      "source_url": "https://lienquan.garena.vn/rss",
      "published_at": "2025-10-21T04:19:14Z",
      "crawled_at": "2025-10-21T05:01:31.722771",
      "category": "tướng",
      "priority": 1
    },
    {
      "id": "b60d77af610e",
      "title": "CHI TIẾT BẢN CẬP NHẬT QUANG MINH & HẮC ÁM 22.10.2025",
      "link": "https://lienquan.garena.vn/chi-tiet-ban-cap-nhat-quang-minh-hac-am-22-10-2025/",
      "summary": "<p>Xin chào các Kiện Tướng, Phiên bản Quang Minh &#38; Hắc Ám chính thức cập nhật vào ngày 22.10.2025 đem tới nhiều trải nghiệm mới trên chiến trường cùng những tính năng độc đáo. Hãy cùng [&#8230;]</p>\n<p>The post <a href=\"https://lienquan.garena.vn/chi-tiet-ban-cap-nhat-quang-minh-hac-am-22-10-2025/\">CHI TIẾT BẢN CẬP NHẬT QUANG MINH &#038; HẮC ÁM 22.10.2025</a> appeared first on <a href=\"https://lienquan.garena.vn\">Liên Quân Mobile</a>.</p>",
      "image_url": null,
      "source": "Liên Quân Mobile Official",
      "source_url": "https://lienquan.garena.vn/rss",
      "published_at": "2025-10-21T04:10:45Z",
      "crawled_at": "2025-10-21T05:01:31.722844",
      "category": "tướng",
      "priority": 1
    },
    {
      "id": "79a7b0d74d9c",
      "title": "TỔNG HỢP SỰ KIỆN 20.10 – 26.10",
      "link": "https://lienquan.garena.vn/tong-hop-su-kien-2010-2610/",
      "summary": "<p>Xin chào các Kiện tướng, Hội đồng xin gửi tới các Kiện tướng lịch sự kiện tại Cửa hàng (20/10– 26/10) như sau: Ngày Sự kiện Sự kiện Thứ 2 (20/10) Giảm giá trang phục [&#8230;]</p>\n<p>The post <a href=\"https://lienquan.garena.vn/tong-hop-su-kien-2010-2610/\">TỔNG HỢP SỰ KIỆN 20.10 &#8211; 26.10</a> appeared first on <a href=\"https://lienquan.garena.vn\">Liên Quân Mobile</a>.</p>",
      "image_url": null,
      "source": "Liên Quân Mobile Official",
      "source_url": "https://lienquan.garena.vn/rss",
      "published_at": "2025-10-21T03:41:00Z",
      "crawled_at": "2025-10-21T04:01:36.853561",
      "category": "tướng",
      "priority": 1
    },
    {
      "id": "9403428d639d",
      "title": "TỔNG KẾT GIAI ĐOẠN 2 – ĐẤU TRƯỜNG DANH VỌNG MÙA ĐÔNG 2025: BỐN CÁI TÊN MẠNH NHẤT TIẾN VÀO PLAY-OFFS, HỌ LÀ AI?",
      "link": "https://lienquan.garena.vn/tong-ket-giai-doan-2-dau-truong-danh-vong-mua-dong-2025-bon-cai-ten-manh-nhat-tien-vao-play-offs-ho-la-ai/",
      "summary": "<p>Super Week – giai đoạn nước rút của vòng bảng Đấu Trường Danh Vọng Mùa Đông 2025 – đang bước vào những ngày thi đấu cuối cùng đầy căng thẳng. Cuộc đua giành tấm vé [&#8230;]</p>\n<p>The post <a href=\"https://lienquan.garena.vn/tong-ket-giai-doan-2-dau-truong-danh-vong-mua-dong-2025-bon-cai-ten-manh-nhat-tien-vao-play-offs-ho-la-ai/\">TỔNG KẾT GIAI ĐOẠN 2 – ĐẤU TRƯỜNG DANH VỌNG MÙA ĐÔNG 2025: BỐN CÁI TÊN MẠNH NHẤT TIẾN VÀO PLAY-OFFS, HỌ LÀ AI?  </a> appeared first on <a href=\"https://lienquan.ga",
      "image_url": null,
      "source": "Liên Quân Mobile Official",
      "source_url": "https://lienquan.garena.vn/rss",
      "published_at": "2025-10-16T08:48:31Z",
      "crawled_at": "2025-10-18T05:06:55.670820",
      "category": "tin tức",
      "priority": 1
    },
    {
      "id": "84f2fedca22a",
      "title": "CHÚC MỪNG COMMUNITY LEADER XUẤT SẮC NHẤT THÁNG 9 NĂM 2025",
      "link": "https://lienquan.garena.vn/chuc-mung-community-leader-xuat-sac-nhat-thang-9-nam-2025/",
      "summary": "<p>Xin chào các Kiện tướng, Hành trình “Ngày hội tựu trường Liên Quân” tháng 9/2025 đã chính thức khép lại, để lại những dấu ấn khó quên trong cộng đồng Kiện Tướng trên toàn quốc.  [&#8230;]</p>\n<p>The post <a href=\"https://lienquan.garena.vn/chuc-mung-community-leader-xuat-sac-nhat-thang-9-nam-2025/\">CHÚC MỪNG COMMUNITY LEADER XUẤT SẮC NHẤT THÁNG 9 NĂM 2025</a> appeared first on <a href=\"https://lienquan.garena.vn\">Liên Quân Mobile</a>.</p>",
      "image_url": null,
      "source": "Liên Quân Mobile Official",
      "source_url": "https://lienquan.garena.vn/rss",
      "published_at": "2025-10-16T05:25:39Z",
      "crawled_at": "2025-10-18T05:06:55.670885",
      "category": "tướng",
      "priority": 1
    },
    {
      "id": "d2596806a084",
      "title": "TỔNG KẾT ĐẤU TRƯỜNG DANH VỌNG MÙA ĐÔNG 2025 VÒNG BẢNG GIAI ĐOẠN 1: ĐẤU TRÍ CĂNG NÃO, TOP 6 LỘ DIỆN",
      "link": "https://lienquan.garena.vn/tong-ket-dau-truong-danh-vong-mua-dong-2025-vong-bang-giai-doan-1-dau-tri-cang-nao-top-6-lo-dien/",
      "summary": "<p>Sau khi ngày vòng 14 khép lại, BXH Vòng bảng Giai đoạn 1 ĐTDV Mùa Đông 2025 đã chính thức có kết quả. Cục diện BXH không có quá nhiều biến động. Trong đó, các [&#8230;]</p>\n<p>The post <a href=\"https://lienquan.garena.vn/tong-ket-dau-truong-danh-vong-mua-dong-2025-vong-bang-giai-doan-1-dau-tri-cang-nao-top-6-lo-dien/\">TỔNG KẾT ĐẤU TRƯỜNG DANH VỌNG MÙA ĐÔNG 2025 VÒNG BẢNG GIAI ĐOẠN 1: ĐẤU TRÍ CĂNG NÃO, TOP 6 LỘ DIỆN</a> appeared first on <a href=\"https://lienquan.garena.vn\">Liên Quân Mobile</a",
      "image_url": null,
      "source": "Liên Quân Mobile Official",
      "source_url": "https://lienquan.garena.vn/rss",
      "published_at": "2025-10-15T03:29:07Z",
      "crawled_at": "2025-10-18T05:06:55.670928",
      "category": "tin tức",
      "priority": 1
    },
    {
      "id": "4bc765fe20a3",
      "title": "TỔNG KẾT ĐỘI HÌNH XUẤT SẮC NHẤT VÀ DIỄN BIẾN LƯỢT VỀ GIAI ĐOẠN 1 ĐẤU TRƯỜNG DANH VỌNG MÙA ĐÔNG 2025",
      "link": "https://lienquan.garena.vn/tong-ket-doi-hinh-xuat-sac-nhat-va-dien-bien-luot-ve-giai-doan-1-dau-truong-danh-vong-mua-dong-2025/",
      "summary": "<p>Khép lại lượt về Đấu Trường Danh Vọng mùa Đông 2025, đội hình xuất sắc nhất giai đoạn cũng đã chính thức lộ diện quy tụ những cái tên thi đấu ổn định, giàu đột [&#8230;]</p>\n<p>The post <a href=\"https://lienquan.garena.vn/tong-ket-doi-hinh-xuat-sac-nhat-va-dien-bien-luot-ve-giai-doan-1-dau-truong-danh-vong-mua-dong-2025/\">TỔNG KẾT ĐỘI HÌNH XUẤT SẮC NHẤT VÀ DIỄN BIẾN LƯỢT VỀ GIAI ĐOẠN 1 ĐẤU TRƯỜNG DANH VỌNG MÙA ĐÔNG 2025</a> appeared first on <a href=\"https://lienquan.garena.vn\">Liên Quân Mobi",
      "image_url": null,
      "source": "Liên Quân Mobile Official",
      "source_url": "https://lienquan.garena.vn/rss",
      "published_at": "2025-10-15T03:21:38Z",
      "crawled_at": "2025-10-18T05:06:55.670977",
      "category": "tin tức",
      "priority": 1
    },
    {
      "id": "0fd71f9c47c3",
      "title": "LỊCH TUẦN THI ĐẤU SUPER WEEK – ĐẤU TRƯỜNG DANH VỌNG MÙA ĐÔNG 2025",
      "link": "https://lienquan.garena.vn/lich-tuan-thi-dau-super-week-dau-truong-danh-vong-mua-dong-2025/",
      "summary": "<p>Bắt đầu từ ngày 08/10 &#8211; 12/10 (Giai đoạn 2) và 19/10 (vòng Play-Offs), tuần thi đấu Super Week chính thức bắt đầu. Tuần thi đấu trực tiếp có khán giả sẽ diễn ra xuyên [&#8230;]</p>\n<p>The post <a href=\"https://lienquan.garena.vn/lich-tuan-thi-dau-super-week-dau-truong-danh-vong-mua-dong-2025/\">LỊCH TUẦN THI ĐẤU SUPER WEEK &#8211; ĐẤU TRƯỜNG DANH VỌNG MÙA ĐÔNG 2025</a> appeared first on <a href=\"https://lienquan.garena.vn\">Liên Quân Mobile</a>.</p>",
      "image_url": null,
      "source": "Liên Quân Mobile Official",
      "source_url": "https://lienquan.garena.vn/rss",
      "published_at": "2025-10-15T03:15:38Z",
      "crawled_at": "2025-10-18T05:06:55.671024",
      "category": "tin tức",
      "priority": 1
    },
    {
      "id": "5255b12b3df1",
      "title": "NHẬN QUÀ SINH NHẬT CỰC HẤP DẪN TẠI CHUỖI SỰ KIỆN CỘNG ĐỒNG SINH NHẬT LIÊN QUÂN 9 TUỔI TỪ NGÀY 18/10 ĐẾN HẾT 31/10",
      "link": "https://lienquan.garena.vn/nhan-qua-sinh-nhat-cuc-hap-dan-tai-chuoi-su-kien-cong-dong-sinh-nhat-lien-quan-9-tuoi-tu-ngay-18-10-den-het-31-10/",
      "summary": "<p>Xin chào các Kiện tướng,  Vậy là Liên Quân Mobile đã chính thức tròn 9 tuổi – đánh dấu một hành trình đáng nhớ của hàng triệu Kiện Tướng trên khắp Việt Nam, nơi chúng [&#8230;]</p>\n<p>The post <a href=\"https://lienquan.garena.vn/nhan-qua-sinh-nhat-cuc-hap-dan-tai-chuoi-su-kien-cong-dong-sinh-nhat-lien-quan-9-tuoi-tu-ngay-18-10-den-het-31-10/\">NHẬN QUÀ SINH NHẬT CỰC HẤP DẪN TẠI CHUỖI SỰ KIỆN CỘNG ĐỒNG SINH NHẬT LIÊN QUÂN 9 TUỔI TỪ NGÀY 18/10 ĐẾN HẾT 31/10</a> appeared first on <a href=\"https:/",
      "image_url": "https://picsum.photos/seed/https://lienquan.garena.vn/nhan-qua-sinh-nhat-cuc-hap-dan-tai-chuoi-su-kien-cong-dong-sinh-nhat-lien-quan-9-tuoi-tu-ngay-18-10-den-het-31-10//400/225",
      "source": "Liên Quân Mobile Official",
      "source_url": "https://lienquan.garena.vn/rss",
      "published_at": "2025-10-14T04:30:35Z",
      "crawled_at": "2025-10-18T05:06:55.671071",
      "category": "tướng",
      "priority": 1
    },
    {
      "id": "11eb3d224359",
      "title": "TỔNG HỢP SỰ KIỆN 13.10 – 19.10",
      "link": "https://lienquan.garena.vn/tong-hop-su-kien-1310-1910/",
      "summary": "<p>Xin chào các Kiện tướng, Hội đồng xin gửi tới các Kiện tướng lịch sự kiện tại Cửa hàng (13/10– 19/10) như sau: Ngày Sự kiện Sự kiện Thứ 2 (13/10) Rương thủy thần: Cơ [&#8230;]</p>\n<p>The post <a href=\"https://lienquan.garena.vn/tong-hop-su-kien-1310-1910/\">TỔNG HỢP SỰ KIỆN 13.10 &#8211; 19.10</a> appeared first on <a href=\"https://lienquan.garena.vn\">Liên Quân Mobile</a>.</p>",
      "image_url": null,
      "source": "Liên Quân Mobile Official",
      "source_url": "https://lienquan.garena.vn/rss",
      "published_at": "2025-10-13T07:48:20Z",
      "crawled_at": "2025-10-18T05:06:55.671108",
      "category": "tướng",
      "priority": 1
    },
    {
      "id": "a5e7115c9b75",
      "title": "THÁNG 10 NÀY NHẬN NGAY CƠ HỘI GIẢM ĐẾN 50K KHI NẠP THẺ GARENA BẰNG VÍ SHOPEEPAY",
      "link": "https://lienquan.garena.vn/thang-10-nay-nhan-ngay-co-hoi-giam-den-50k-khi-nap-the-garena-bang-vi-shopeepay/",
      "summary": "<p>Mưa rơi không làm chùn bước &#8220;dân chơi&#8221;  Tháng 10 này nhận ngay cơ hội giảm đến 50K khi nạp thẻ Garena bằng ví ShopeePay  Đặc biệt: giảm 20% tối đa 20K khi nhập mã [&#8230;]</p>\n<p>The post <a href=\"https://lienquan.garena.vn/thang-10-nay-nhan-ngay-co-hoi-giam-den-50k-khi-nap-the-garena-bang-vi-shopeepay/\">THÁNG 10 NÀY NHẬN NGAY CƠ HỘI GIẢM ĐẾN 50K KHI NẠP THẺ GARENA BẰNG VÍ SHOPEEPAY</a> appeared first on <a href=\"https://lienquan.garena.vn\">Liên Quân Mobile</a>.</p>",
      "image_url": null,
      "source": "Liên Quân Mobile Official",
      "source_url": "https://lienquan.garena.vn/rss",
      "published_at": "2025-10-02T04:38:16Z",
      "crawled_at": "2025-10-05T09:24:12.930299",
      "category": "tin tức",
      "priority": 1
    },
    {
      "id": "88b607961ca8",
      "title": "TỔNG KẾT ĐẤU TRƯỜNG DANH VỌNG MÙA ĐÔNG 2025 – VÒNG 14: BOX ĐÁNH RƠI TOP 4, FPT ĐẢ BẠI “NHÀ VUA AOG” THUYẾT PHỤC",
      "link": "https://lienquan.garena.vn/tong-ket-dau-truong-danh-vong-mua-dong-2025-vong-14-box-danh-roi-top-4-fpt-da-bai-nha-vua-aog-thuyet-phuc/",
      "summary": "<p>ĐTDV Mùa Đông 2025 bước sang vòng 14, tiếp nối những cuộc so tài căng não bằng loạt diễn biến khó lường và khép lại tuần đấu với một số thay đổi trên BXH. Trong [&#8230;]</p>\n<p>The post <a href=\"https://lienquan.garena.vn/tong-ket-dau-truong-danh-vong-mua-dong-2025-vong-14-box-danh-roi-top-4-fpt-da-bai-nha-vua-aog-thuyet-phuc/\">TỔNG KẾT ĐẤU TRƯỜNG DANH VỌNG MÙA ĐÔNG 2025 &#8211; VÒNG 14: BOX ĐÁNH RƠI TOP 4, FPT ĐẢ BẠI “NHÀ VUA AOG” THUYẾT PHỤC</a> appeared first on <a href=\"https://lienquan.",
      "image_url": null,
      "source": "Liên Quân Mobile Official",
      "source_url": "https://lienquan.garena.vn/rss",
      "published_at": "2025-10-02T04:26:15Z",
      "crawled_at": "2025-10-05T09:24:12.930299",
      "category": "tin tức",
      "priority": 1
    },
    {
      "id": "40dac716377a",
      "title": "TỔNG KẾT ĐẤU TRƯỜNG DANH VỌNG MÙA ĐÔNG 2025 – VÒNG 13: BƯỚC CHẠY ĐÀ HOÀN HẢO CỦA CÁC ĐỘI TUYỂN TRƯỚC VÒNG BẢNG GIAI ĐOẠN 2",
      "link": "https://lienquan.garena.vn/tong-ket-dau-truong-danh-vong-mua-dong-2025-vong-13-buoc-chay-da-hoan-hao-cua-cac-doi-tuyen-truoc-vong-bang-giai-doan-2/",
      "summary": "<p>Vòng 13 kết thúc với những kết quả có lợi cho các đội tuyển nhóm trên, có thể nói những cái tên bước tiếp vào giai đoạn 2 đã được chốt hạ, hãy cùng chúng [&#8230;]</p>\n<p>The post <a href=\"https://lienquan.garena.vn/tong-ket-dau-truong-danh-vong-mua-dong-2025-vong-13-buoc-chay-da-hoan-hao-cua-cac-doi-tuyen-truoc-vong-bang-giai-doan-2/\">TỔNG KẾT ĐẤU TRƯỜNG DANH VỌNG MÙA ĐÔNG 2025 – VÒNG 13: BƯỚC CHẠY ĐÀ HOÀN HẢO CỦA CÁC ĐỘI TUYỂN TRƯỚC VÒNG BẢNG GIAI ĐOẠN 2</a> appeared first on <a href=\"https",
      "image_url": null,
      "source": "Liên Quân Mobile Official",
      "source_url": "https://lienquan.garena.vn/rss",
      "published_at": "2025-10-02T03:57:19Z",
      "crawled_at": "2025-10-05T09:24:12.930299",
      "category": "tin tức",
      "priority": 1
    },
    {
      "id": "bfee130936a1",
      "title": "TỔNG KẾT ĐẤU TRƯỜNG DANH VỌNG MÙA ĐÔNG 2025 – VÒNG 11+12: FPT PHONG ĐỘ HỦY DIỆT, BOX BẢO TOÀN TOP 4",
      "link": "https://lienquan.garena.vn/tong-ket-dau-truong-danh-vong-mua-dong-2025-vong-1112-fpt-phong-do-huy-diet-box-bao-toan-top-4/",
      "summary": "<p>ĐTDV Mùa Đông 2025 bước sang vòng 11,12 với loạt trận đấu kịch tính. FPT x Flash liên tục khẳng định sức mạnh với chiến thắng áp đảo, BOX Gaming thành công giữ vững vị [&#8230;]</p>\n<p>The post <a href=\"https://lienquan.garena.vn/tong-ket-dau-truong-danh-vong-mua-dong-2025-vong-1112-fpt-phong-do-huy-diet-box-bao-toan-top-4/\">TỔNG KẾT ĐẤU TRƯỜNG DANH VỌNG MÙA ĐÔNG 2025 &#8211; VÒNG 11+12: FPT PHONG ĐỘ HỦY DIỆT, BOX BẢO TOÀN TOP 4</a> appeared first on <a href=\"https://lienquan.garena.vn\">Liên ",
      "image_url": null,
      "source": "Liên Quân Mobile Official",
      "source_url": "https://lienquan.garena.vn/rss",
      "published_at": "2025-10-02T03:36:48Z",
      "crawled_at": "2025-10-05T09:24:12.930299",
      "category": "tin tức",
      "priority": 1
    },
    {
      "id": "news001",
      "title": "Tướng mới Charlotte sắp ra mắt với kỹ năng đặc biệt",
      "link": "https://example.com/charlotte-new-hero",
      "summary": "Charlotte - tướng pháp sư mới với khả năng điều khiển thời gian sẽ được ra mắt trong bản cập nhật tiếp theo của Liên Quân Mobile.",
      "source": "GameK.vn",
      "source_url": "https://gamek.vn",
      "published_at": "2025-09-30T08:00:00Z",
      "crawled_at": "2025-09-30T10:00:00Z",
      "category": "tướng",
      "priority": 1
    },
    {
      "id": "news002",
      "title": "Skin Legendary mới cho Nakroth - Thần Chiến Binh",
      "link": "https://example.com/nakroth-legendary-skin",
      "summary": "Skin Legendary mới của Nakroth với hiệu ứng đặc biệt và animation độc đáo sẽ có mặt trong shop từ ngày mai.",
      "source": "VnExpress",
      "source_url": "https://vnexpress.net",
      "published_at": "2025-09-29T15:30:00Z",
      "crawled_at": "2025-09-30T10:00:00Z",
      "category": "skin",
      "priority": 2
    },
    {
      "id": "news003",
      "title": "Bản cập nhật 5.4.0: Cân bằng tướng và sửa lỗi",
      "link": "https://example.com/patch-5-4-0",
      "summary": "Bản cập nhật 5.4.0 sẽ cân bằng lại sức mạnh của các tướng và sửa nhiều lỗi bug quan trọng trong game.",
      "source": "Zing News",
      "source_url": "https://zingnews.vn",
      "published_at": "2025-09-29T12:00:00Z",
      "crawled_at": "2025-09-30T10:00:00Z",
      "category": "cập nhật",
      "priority": 3
    },
    {
      "id": "news004",
      "title": "ĐTDV Mùa Đông 2025: Saigon Phantom giành chiến thắng",
      "link": "https://example.com/sgp-victory",
      "summary": "Saigon Phantom đã đánh bại FPT X Flash trong trận chung kết ĐTDV Mùa Đông 2025 với tỷ số 3-1.",
      "source": "Dân Trí",
      "source_url": "https://dantri.com.vn",
      "published_at": "2025-09-28T20:00:00Z",
      "crawled_at": "2025-09-30T10:00:00Z",
      "category": "esports",
      "priority": 4
    },
    {
      "id": "news005",
      "title": "Meta mới: Tướng đi rừng đang thống trị rank cao",
      "link": "https://example.com/jungle-meta",
      "summary": "Các tướng đi rừng như Nakroth, Kriknak đang có tỷ lệ thắng cao nhất tại rank Cao Thủ và Thách Đấu.",
      "source": "GameK.vn",
      "source_url": "https://gamek.vn",
      "published_at": "2025-09-28T10:00:00Z",
      "crawled_at": "2025-09-30T10:00:00Z",
      "category": "meta",
      "priority": 5
    },
    {
      "id": "news006",
      "title": "Hướng dẫn build đồ cho tướng mới Charlotte",
      "link": "https://example.com/charlotte-build-guide",
      "summary": "Hướng dẫn chi tiết cách build đồ, bảng ngọc và combo kỹ năng cho tướng Charlotte để đạt hiệu quả tối đa.",
      "source": "VnExpress",
      "source_url": "https://vnexpress.net",
      "published_at": "2025-09-27T14:00:00Z",
      "crawled_at": "2025-09-30T10:00:00Z",
      "category": "meta",
      "priority": 6
    },
    {
      "id": "news007",
      "title": "Sự kiện đặc biệt: Nhân đôi kinh nghiệm và vàng",
      "link": "https://example.com/double-exp-gold-event",
      "summary": "Sự kiện đặc biệt cuối tuần này sẽ nhân đôi kinh nghiệm và vàng kiếm được trong các trận đấu.",
      "source": "Zing News",
      "source_url": "https://zingnews.vn",
      "published_at": "2025-09-27T09:00:00Z",
      "crawled_at": "2025-09-30T10:00:00Z",
      "category": "tin tức",
      "priority": 7
    },
    {
      "id": "news008",
      "title": "Tier List tướng tháng 9: Ai đang mạnh nhất?",
      "link": "https://example.com/september-tier-list",
      "summary": "Danh sách xếp hạng tướng mạnh nhất tháng 9 dựa trên tỷ lệ thắng và độ phổ biến tại các rank cao.",
      "source": "Dân Trí",
      "source_url": "https://dantri.com.vn",
      "published_at": "2025-09-26T16:00:00Z",
      "crawled_at": "2025-09-30T10:00:00Z",
      "category": "meta",
      "priority": 8
    },
    {
      "id": "news009",
      "title": "Skin mới cho Alice - Công chúa Băng Giá",
      "link": "https://example.com/alice-ice-princess-skin",
      "summary": "Skin mới của Alice với chủ đề công chúa băng giá sẽ có hiệu ứng đặc biệt và animation đẹp mắt.",
      "source": "GameK.vn",
      "source_url": "https://gamek.vn",
      "published_at": "2025-09-26T11:00:00Z",
      "crawled_at": "2025-09-30T10:00:00Z",
      "category": "skin",
      "priority": 9
    },
    {
      "id": "fb539eba0d36",
      "title": "TỔNG HỢP SỰ KIỆN 29.09 – 05.10",
      "link": "https://lienquan.garena.vn/tong-hop-su-kien-2909-0510/",
      "summary": "<p>Xin chào các Kiện tướng, Hội đồng xin gửi tới các Kiện tướng lịch sự kiện tại Cửa hàng (29/09– 05/10) như sau: Ngày Sự kiện Sự kiện Thứ 2 (29/09) Combo rương tháng 9: [&#8230;]</p>\n<p>The post <a href=\"https://lienquan.garena.vn/tong-hop-su-kien-2909-0510/\">TỔNG HỢP SỰ KIỆN 29.09 &#8211; 05.10</a> appeared first on <a href=\"https://lienquan.garena.vn\">Liên Quân Mobile</a>.</p>",
      "source": "Liên Quân Mobile Official",
      "source_url": "https://lienquan.garena.vn/rss",
      "published_at": "2025-09-26T09:58:05Z",
      "crawled_at": "2025-09-30T13:03:38.354251",
      "category": "tướng",
      "priority": 5
    },
    {
      "id": "news010",
      "title": "Giải đấu Liên Quân Mobile quốc tế sắp diễn ra",
      "link": "https://example.com/international-tournament",
      "summary": "Giải đấu Liên Quân Mobile quốc tế với sự tham gia của các đội tuyển hàng đầu thế giới sẽ diễn ra vào tháng 11.",
      "source": "VnExpress",
      "source_url": "https://vnexpress.net",
      "published_at": "2025-09-25T18:00:00Z",
      "crawled_at": "2025-09-30T10:00:00Z",
      "category": "esports",
      "priority": 10
    },
    {
      "id": "news011",
      "title": "Bảng ngọc mới cho tướng đi rừng mùa này",
      "link": "https://example.com/jungle-arcana-guide",
      "summary": "Hướng dẫn chọn bảng ngọc phù hợp cho các tướng đi rừng trong meta hiện tại để tối ưu hóa sức mạnh.",
      "source": "Zing News",
      "source_url": "https://zingnews.vn",
      "published_at": "2025-09-25T13:00:00Z",
      "crawled_at": "2025-09-30T10:00:00Z",
      "category": "meta",
      "priority": 11
    },
    {
      "id": "e50e6e4a459d",
      "title": "TỔNG KẾT ĐẤU TRƯỜNG DANH VỌNG MÙA ĐÔNG 2025 – VÒNG 9 + 10: 1S GỤC NGÃ TRƯỚC SGP – FPT NGỰ TRỊ NGÔI ĐẦU",
      "link": "https://lienquan.garena.vn/tong-ket-dau-truong-danh-vong-mua-dong-2025-vong-9-10-1s-guc-nga-truoc-sgp-fpt-ngu-tri-ngoi-dau/",
      "summary": "<p>Vòng 9 và 10 của Đấu Trường Danh Vọng Mùa Đông 2025 đã chính thức khép lại. Hãy cùng nhìn lại những diễn biến đáng chú ý cũng như cục diện trên bảng xếp hạng [&#8230;]</p>\n<p>The post <a href=\"https://lienquan.garena.vn/tong-ket-dau-truong-danh-vong-mua-dong-2025-vong-9-10-1s-guc-nga-truoc-sgp-fpt-ngu-tri-ngoi-dau/\">TỔNG KẾT ĐẤU TRƯỜNG DANH VỌNG MÙA ĐÔNG 2025 – VÒNG 9 + 10: 1S GỤC NGÃ TRƯỚC SGP &#8211; FPT NGỰ TRỊ NGÔI ĐẦU </a> appeared first on <a href=\"https://lienquan.garena.vn\">Liên Quân ",
      "source": "Liên Quân Mobile Official",
      "source_url": "https://lienquan.garena.vn/rss",
      "published_at": "2025-09-25T09:47:51Z",
      "crawled_at": "2025-09-30T13:03:38.354251",
      "category": "tin tức",
      "priority": 5
    },
    {
      "id": "7f0b44e0bb60",
      "title": "Tổng hợp sự kiện 22.09 – 28.09",
      "link": "https://lienquan.garena.vn/11172-2/",
      "summary": "<p>Xin chào các Kiện tướng, Hội đồng xin gửi tới các Kiện tướng lịch sự kiện tại Cửa hàng (22/09– 28/08) như sau: Ngày Sự kiện Sự kiện Thứ 2 (22/09) Sự kiện Sự trở [&#8230;]</p>\n<p>The post <a href=\"https://lienquan.garena.vn/11172-2/\">Tổng hợp sự kiện 22.09 &#8211; 28.09</a> appeared first on <a href=\"https://lienquan.garena.vn\">Liên Quân Mobile</a>.</p>",
      "source": "Liên Quân Mobile Official",
      "source_url": "https://lienquan.garena.vn/rss",
      "published_at": "2025-09-25T08:26:54Z",
      "crawled_at": "2025-09-30T13:03:38.354251",
      "category": "tướng",
      "priority": 5
    },
    {
      "id": "news012",
      "title": "Cập nhật hệ thống báo cáo và chống hack",
      "link": "https://example.com/anti-cheat-update",
      "summary": "Hệ thống chống hack và báo cáo người chơi gian lận đã được cải tiến để đảm bảo công bằng trong game.",
      "source": "Dân Trí",
      "source_url": "https://dantri.com.vn",
      "published_at": "2025-09-24T20:00:00Z",
      "crawled_at": "2025-09-30T10:00:00Z",
      "category": "cập nhật",
      "priority": 12
    },
    {
      "id": "02d1939ffce3",
      "title": "THÔNG BÁO TRẢI NGHIỆM GIAO DIỆN NẠP THẺ 2.0",
      "link": "https://lienquan.garena.vn/thong-bao-trai-nghiem-giao-dien-nap-the-2-0/",
      "summary": "<p>THÔNG BÁO TRẢI NGHIỆM GIAO DIỆN NẠP THẺ 2.0 Nhằm mang đến trải nghiệm nạp thẻ tối ưu hơn cho người chơi, Garena sẽ triển khai thử nghiệm giao diện nạp thẻ phiên bản 2.0 [&#8230;]</p>\n<p>The post <a href=\"https://lienquan.garena.vn/thong-bao-trai-nghiem-giao-dien-nap-the-2-0/\">THÔNG BÁO TRẢI NGHIỆM GIAO DIỆN NẠP THẺ 2.0</a> appeared first on <a href=\"https://lienquan.garena.vn\">Liên Quân Mobile</a>.</p>",
      "source": "Liên Quân Mobile Official",
      "source_url": "https://lienquan.garena.vn/rss",
      "published_at": "2025-09-24T02:00:25Z",
      "crawled_at": "2025-09-30T13:03:38.354251",
      "category": "tin tức",
      "priority": 5
    },
    {
      "id": "40a85ed4ae5b",
      "title": "TIẾP TỤC BÙNG NỔ CHUỖI SỰ KIỆN THÁNG 9 – NGÀY HỘI TỰU TRƯỜNG GIAI ĐOẠN 4 (TUẦN 27/09 – 30/09)",
      "link": "https://lienquan.garena.vn/tiep-tuc-bung-no-chuoi-su-kien-thang-9-ngay-hoi-tuu-truong-giai-doan-4-tuan-27-09-30-09/",
      "summary": "<p>Xin chào các Kiện Tướng, Chuỗi sự kiện cộng đồng tháng 9 đã bước vào tuần cuối cùng (27/09 – 30/09) với nhiều hoạt động cực kỳ sôi động trên toàn quốc. Đây là cơ [&#8230;]</p>\n<p>The post <a href=\"https://lienquan.garena.vn/tiep-tuc-bung-no-chuoi-su-kien-thang-9-ngay-hoi-tuu-truong-giai-doan-4-tuan-27-09-30-09/\">TIẾP TỤC BÙNG NỔ CHUỖI SỰ KIỆN THÁNG 9 &#8211; NGÀY HỘI TỰU TRƯỜNG GIAI ĐOẠN 4 (TUẦN 27/09 – 30/09)</a> appeared first on <a href=\"https://lienquan.garena.vn\">Liên Quân Mobile</a>.</p",
      "source": "Liên Quân Mobile Official",
      "source_url": "https://lienquan.garena.vn/rss",
      "published_at": "2025-09-23T08:20:44Z",
      "crawled_at": "2025-09-30T13:03:38.354251",
      "category": "tướng",
      "priority": 5
    },
    {
      "id": "caef9a979f40",
      "title": "Không phải Quan Vũ hay Trương Phi, vị tướng này hạ nhiều địch nhất thời Tam Quốc",
      "link": "https://gamek.vn/khong-phai-quan-vu-hay-truong-phi-vi-tuong-nay-ha-nhieu-dich-nhat-thoi-tam-quoc-178251029150107105.chn",
      "summary": "Quan Vũ và Trương Phi nổi danh là những mãnh tướng vô song của nhà Thục, nhưng người giữ kỷ lục hạ nhiều địch nhất thời Tam Quốc lại thuộc về một người ít ngờ tới.",
      "image_url": "https://gamek.mediacdn.vn/zoom/1200_900/133514250583805952/2025/10/29/avatar1761724634132-17617246346321046203639-0-26-274-465-crop-1761724676693768086802.jpg",
      "source": "GameK.vn",
      "source_url": "https://gamek.vn/rss",
      "published_at": null,
      "crawled_at": "2025-10-31T06:01:38.614711",
      "category": "tướng",
      "priority": 2
    },
    {
      "id": "4c0c1cbe2ab1",
      "title": "Những bậc Tông sư vĩ đại của tiểu thuyết Kim Dung, có 2 nhân vật còn chưa bao giờ \"lên hình\"",
      "link": "https://gamek.vn/nhung-bac-tong-su-vi-dai-cua-tieu-thuyet-kim-dung-co-2-nhan-vat-con-chua-bao-gio-len-hinh-178251030212207939.chn",
      "summary": "Đây là những bậc Tông sư vĩ đại, không chỉ là cao thủ võ lâm mà còn đào tạo ra những đệ tử toàn tài của tiểu thuyết Kim Dung.",
      "image_url": "https://gamek.mediacdn.vn/zoom/1200_900/133514250583805952/2025/10/30/avatar1761839762532-1761839762952128357725.png",
      "source": "GameK.vn",
      "source_url": "https://gamek.vn/rss",
      "published_at": null,
      "crawled_at": "2025-10-30T16:01:50.312333",
      "category": "tin tức",
      "priority": 2
    },
    {
      "id": "180720b54a1e",
      "title": "Rò rỉ Genshin Impact, một nhân vật quan trọng sẽ xuất hiện trong phiên bản mới",
      "link": "https://gamek.vn/ro-ri-genshin-impact-mot-nhan-vat-quan-trong-se-xuat-hien-trong-phien-ban-moi-178251029155304564.chn",
      "summary": "Các fan Genshin Impact sẽ có nhiều lý do để chờ đợi bản cập nhật mới này.",
      "image_url": "https://gamek.mediacdn.vn/zoom/1200_900/133514250583805952/2025/10/30/avatar1761791385454-1761791385905857968289.png",
      "source": "GameK.vn",
      "source_url": "https://gamek.vn/rss",
      "published_at": null,
      "crawled_at": "2025-10-30T09:01:37.163734",
      "category": "cập nhật",
      "priority": 2
    },
    {
      "id": "2e27921d6fd8",
      "title": "Chung kết Audition Vietnam Championship 2025: Đã tìm ra nhà vô địch toàn quốc",
      "link": "https://gamek.vn/chung-ket-audition-vietnam-championship-2025-da-tim-ra-nha-vo-dich-toan-quoc-178251030125803435.chn",
      "summary": "Audition Vietnam Championship 2025 (AVC 2025) đã chính thức khép lại trong không khí cuồng nhiệt tại Hà Nội, đánh dấu cột mốc ấn tượng trong lịch sử eSports Audition Việt Nam.",
      "image_url": "https://gamek.mediacdn.vn/zoom/1200_900/133514250583805952/2025/10/30/photo1761644914074-1761644914192846811900-1761803885187988531859.jpg",
      "source": "GameK.vn",
      "source_url": "https://gamek.vn/rss",
      "published_at": null,
      "crawled_at": "2025-10-30T07:01:35.824056",
      "category": "esports",
      "priority": 2
    },
    {
      "id": "8a5fbd90258a",
      "title": "Cosplay tướng tủ, Quỳnh Bei cực slay khiến fan trầm trồ",
      "link": "https://gamek.vn/cosplay-tuong-tu-quynh-bei-cuc-slay-khien-fan-tram-tro-178251028141419073.chn",
      "summary": "Quỳnh Bei tiếp tục \"đốn tim\" cộng đồng game thủ.",
      "image_url": "https://gamek.mediacdn.vn/zoom/1200_900/133514250583805952/2025/10/28/4-1761625525774248324588-1761635434058-17616354346761216822202-140-0-343-324-crop-17616355606951605987134.jpg",
      "source": "GameK.vn",
      "source_url": "https://gamek.vn/rss",
      "published_at": null,
      "crawled_at": "2025-10-28T12:01:48.762069",
      "category": "tướng",
      "priority": 2
    },
    {
      "id": "400de09a5618",
      "title": "Màn cosplay Violet Huyết Ma Thần khiến anh em game thủ ngất ngây mê đắm",
      "link": "https://gamek.vn/man-cosplay-violet-huyet-ma-than-khien-anh-em-game-thu-ngat-ngay-me-dam-17825102709152107.chn",
      "summary": "Anh em Liên Quân lại được dịp \"điên đảo\" với màn cosplay này.",
      "image_url": "https://gamek.mediacdn.vn/zoom/1200_900/133514250583805952/2025/10/27/photo-1761530389251-17615303898991506345807-377-0-1068-1106-crop-17615459950061926814340.png",
      "source": "GameK.vn",
      "source_url": "https://gamek.vn/rss",
      "published_at": null,
      "crawled_at": "2025-10-28T10:01:37.939259",
      "category": "tin tức",
      "priority": 2
    },
    {
      "id": "0237b57a8df0",
      "title": "Màn cosplay Veres khiến fan Liên Quân không thể nào rời mắt",
      "link": "https://gamek.vn/man-cosplay-veres-khien-fan-lien-quan-khong-the-nao-roi-mat-178251026001046339.chn",
      "summary": "Anh em Liên Quân hẳn rất thích màn cosplay này.",
      "image_url": "https://gamek.mediacdn.vn/zoom/1200_900/133514250583805952/2025/10/26/photo-1761411541774-17614115421781618554665-55-0-524-750-crop-1761453026456602491528.png",
      "source": "GameK.vn",
      "source_url": "https://gamek.vn/rss",
      "published_at": null,
      "crawled_at": "2025-10-27T11:01:57.381893",
      "category": "tin tức",
      "priority": 2
    },
    {
      "id": "44b817032c58",
      "title": "Vị tướng duy nhất Faker sẽ không bao giờ làm skin CKTG kể cả vô địch",
      "link": "https://gamek.vn/vi-tuong-duy-nhat-faker-se-khong-bao-gio-lam-skin-cktg-ke-ca-vo-dich-178251027120030952.chn",
      "summary": "Với Faker, luôn có những ngoại lệ theo quy tắc của anh.",
      "image_url": "https://gamek.mediacdn.vn/zoom/1200_900/133514250583805952/2025/10/27/avatar1761552297286-17615522976751636359900.png",
      "source": "GameK.vn",
      "source_url": "https://gamek.vn/rss",
      "published_at": null,
      "crawled_at": "2025-10-27T09:02:02.565715",
      "category": "tướng",
      "priority": 2
    },
    {
      "id": "b9b336a11915",
      "title": "Valve tung bản cập nhật mới cho CS2, một người chơi tuyên bố mất vợ, mất con vì cú sốc từ thị trường game",
      "link": "https://gamek.vn/valve-tung-ban-cap-nhat-moi-cho-cs2-mot-nguoi-choi-tuyen-bo-mat-vo-mat-con-vi-cu-soc-tu-thi-truong-game-178251024213459009.chn",
      "summary": "Câu chuyện của anh chàng game thủ khiến khá nhiều người phải suy ngẫm.",
      "image_url": "https://gamek.mediacdn.vn/zoom/1200_900/133514250583805952/2025/10/25/avatar1761362048094-1761362048423107002686.png",
      "source": "GameK.vn",
      "source_url": "https://gamek.vn/rss",
      "published_at": null,
      "crawled_at": "2025-10-26T14:01:32.267546",
      "category": "cập nhật",
      "priority": 2
    },
    {
      "id": "d1b145893e9e",
      "title": "Genshin Impact mang tới tin buồn trong bản cập nhật 6.2",
      "link": "https://gamek.vn/genshin-impact-mang-toi-tin-buon-trong-ban-cap-nhat-62-178251024222724487.chn",
      "summary": "Có lẽ, đây là điều mà không game thủ nào mong muốn.",
      "image_url": "https://gamek.mediacdn.vn/zoom/1200_900/133514250583805952/2025/10/25/thumb-photo-1761319000545-17613190012541767069272-17613191053611400373176-107-171-929-1486-crop-1761370265748937473058.png",
      "source": "GameK.vn",
      "source_url": "https://gamek.vn/rss",
      "published_at": null,
      "crawled_at": "2025-10-25T10:01:43.117834",
      "category": "cập nhật",
      "priority": 2
    },
    {
      "id": "c74e841895f8",
      "title": "8 mãnh tướng mạnh nhất Tam Quốc chí: Bất ngờ với thứ hạng Quan Vũ, Trương Phi",
      "link": "https://gamek.vn/8-manh-tuong-manh-nhat-tam-quoc-chi-bat-ngo-voi-thu-hang-quan-vu-truong-phi-178251021152309757.chn",
      "summary": "Bảng xếp hạng 8 mãnh tướng mạnh nhất thời Tam Quốc gồm những ai?",
      "image_url": "https://gamek.mediacdn.vn/zoom/1200_900/133514250583805952/2025/10/21/avatar1761034869370-176103487114191676881-0-88-275-528-crop-17610349130041260354493.png",
      "source": "GameK.vn",
      "source_url": "https://gamek.vn/rss",
      "published_at": null,
      "crawled_at": "2025-10-24T15:01:47.853988",
      "category": "tướng",
      "priority": 2
    },
    {
      "id": "e3faa662d9f0",
      "title": "FC Mobile chấn động cộng đồng khi mang siêu giải đấu quốc tế cùng huyền thoại Kaká, Figo \"đổ bộ\" Việt Nam",
      "link": "https://gamek.vn/fc-mobile-chan-dong-cong-dong-khi-mang-sieu-giai-dau-quoc-te-cung-huyen-thoai-kaka-figo-do-bo-viet-nam-178251024111247996.chn",
      "summary": "Hai huyền thoại Kaká, Figo sẽ xuất hiện trong ngày ra mắt giải đấu Esports quốc tế cực lớn của FC Mobile Việt Nam.",
      "image_url": "https://gamek.mediacdn.vn/zoom/1200_900/133514250583805952/2025/10/24/avatar1761278837645-17612788382792146518061.png",
      "source": "GameK.vn",
      "source_url": "https://gamek.vn/rss",
      "published_at": null,
      "crawled_at": "2025-10-24T06:01:52.086034",
      "category": "esports",
      "priority": 2
    },
    {
      "id": "272a559f630a",
      "title": "4 \"trùm cuối\" nhưng chưa từng lộ mặt trong tiểu thuyết Kim Dung",
      "link": "https://gamek.vn/4-trum-cuoi-nhung-chua-tung-lo-mat-trong-tieu-thuyet-kim-dung-178251019180358723.chn",
      "summary": "Đây là 4 đại cao thủ huyền thoại võ lâm nhưng chưa từng lộ mặt trong tiểu thuyết Kim Dung.",
      "image_url": "https://gamek.mediacdn.vn/zoom/1200_900/133514250583805952/2025/10/20/avatar1760970083589-17609700839521801042055.png",
      "source": "GameK.vn",
      "source_url": "https://gamek.vn/rss",
      "published_at": null,
      "crawled_at": "2025-10-20T15:01:42.045940",
      "category": "tin tức",
      "priority": 2
    },
    {
      "id": "a07cff2fde6a",
      "title": "Đông Phương Bất Bại, Phong Thanh Dương và Phương Chứng đại sư đối đầu, ai thắng?",
      "link": "https://gamek.vn/dong-phuong-bat-bai-phong-thanh-duong-va-phuong-chung-dai-su-doi-dau-ai-thang-178251020161121989.chn",
      "summary": "Trong 3 vị đại cao thủ này, ai là người mạnh nhất?",
      "image_url": "https://gamek.mediacdn.vn/zoom/1200_900/133514250583805952/2025/10/20/avatar1760951350676-17609513511821802509747-1-117-275-555-crop-17609515238252078556209.png",
      "source": "GameK.vn",
      "source_url": "https://gamek.vn/rss",
      "published_at": null,
      "crawled_at": "2025-10-20T13:10:02.821902",
      "category": "tin tức",
      "priority": 2
    },
    {
      "id": "18ccaf5e65e2",
      "title": "Cao thủ bí ẩn nhất của Kim Dung: Kiếm pháp ngang Độc Cô Cầu Bại nhưng bị tác giả 'gạt phăng' khỏi võ lâm",
      "link": "https://gamek.vn/cao-thu-bi-an-nhat-cua-kim-dung-kiem-phap-ngang-doc-co-cau-bai-nhung-bi-tac-gia-gat-phang-khoi-vo-lam-178251017173001824.chn",
      "summary": "Cao thủ này là ai?",
      "image_url": "https://gamek.mediacdn.vn/zoom/1200_900/133514250583805952/2025/10/17/avatar1760696888554-17606968894721538001452.jpg",
      "source": "GameK.vn",
      "source_url": "https://gamek.vn/rss",
      "published_at": null,
      "crawled_at": "2025-10-18T10:01:42.205969",
      "category": "tin tức",
      "priority": 2
    },
    {
      "id": "8e8ecb249c40",
      "title": "Dàn tướng đạt tỷ lệ thắng cao nhất CKTG 2025 tính đến hiện tại, T1 có thể tận dụng",
      "link": "https://gamek.vn/dan-tuong-dat-ty-le-thang-cao-nhat-cktg-2025-tinh-den-hien-tai-t1-co-the-tan-dung-178251018115558273.chn",
      "summary": "4/5 tướng LMHT trong danh sách này đều rất thuận tay T1.",
      "image_url": "https://gamek.mediacdn.vn/zoom/1200_900/133514250583805952/2025/10/18/cktg-tuong-lmht-4-1760763339252274772140-0-0-1250-2000-crop-17607633470481675791157.jpg",
      "source": "GameK.vn",
      "source_url": "https://gamek.vn/rss",
      "published_at": null,
      "crawled_at": "2025-10-18T09:01:43.177169",
      "category": "tướng",
      "priority": 2
    },
    {
      "id": "6e21f484828e",
      "title": "Đây là 5 đại cao thủ được đánh giá mạnh nhất truyện Kim Dung, không có Kiều Phong",
      "link": "https://gamek.vn/day-la-5-dai-cao-thu-duoc-danh-gia-manh-nhat-truyen-kim-dung-khong-co-kieu-phong-178251004130138056.chn",
      "summary": "Đây là 5 đại cao thủ trong toàn bộ các tiểu thuyết võ hiệp của Kim Dung, nhưng không có tên của \"Chiến thần\" Kiều Phong.",
      "image_url": "https://gamek.mediacdn.vn/zoom/1200_900/133514250583805952/2025/10/4/avatar1759576434329-1759576434620448722307.png",
      "source": "GameK.vn",
      "source_url": "https://gamek.vn/rss",
      "published_at": null,
      "crawled_at": "2025-10-05T09:24:14.131836",
      "category": "tin tức",
      "priority": 2
    },
    {
      "id": "2ffb66a446d8",
      "title": "Bom tấn gây sốt khi hợp tác với Starcraft, tung skin khiến game thủ choáng váng, giá lên tới gần 5 triệu",
      "link": "https://gamek.vn/bom-tan-gay-sot-khi-hop-tac-voi-starcraft-tung-skin-khien-game-thu-choang-vang-gia-len-toi-gan-5-trieu-178250929085321357.chn",
      "summary": "Các game thủ Diablo 4 đã rất sốc trước mức giá này.",
      "image_url": "https://gamek.mediacdn.vn/zoom/1200_900/133514250583805952/2025/9/29/avatar1759111015732-17591110160011042916452.png",
      "source": "GameK.vn",
      "source_url": "https://gamek.vn/rss",
      "published_at": null,
      "crawled_at": "2025-09-30T13:08:14.237682",
      "category": "skin",
      "priority": 2
    },
    {
      "id": "ffe2a6d3f0ff",
      "title": "Nữ game thủ \"Tung Hoang\" nóng bỏng với trang phục áo tắm, game thủ Liên Quân liên tưởng tới skin \"Tiệc bãi biển\"",
      "link": "https://gamek.vn/nu-game-thu-tung-hoang-nong-bong-voi-trang-phuc-ao-tam-game-thu-lien-quan-lien-tuong-toi-skin-tiec-bai-bien-178250929130934725.chn",
      "summary": "Bích Phương vẫn luôn là nữ game thủ \"quốc dân\" đối với cộng đồng.",
      "image_url": "https://gamek.mediacdn.vn/zoom/1200_900/133514250583805952/2025/9/29/photo-1759125487546-17591254878751649130488-723-0-1623-1440-crop-17591358006341335273965.png",
      "source": "GameK.vn",
      "source_url": "https://gamek.vn/rss",
      "published_at": null,
      "crawled_at": "2025-09-30T13:08:14.237682",
      "category": "skin",
      "priority": 2
    }
  ]
}