{
  "videos": [
    {
      "videoId": "q__zHhTBD-8",
      "title": "Cách best Paine gank team bạn nghẹt thở vì combo quá mạnh",
      "source": "youtube",
      "publishedAt": "2026-04-29T06:04:00Z"
    },
    {
      "videoId": "6PA7hPZuLM0",
      "title": "Tướng mới Flowborn hệ pháp sư combo mỏi cả tay vẫn thua! vì sao",
      "source": "youtube",
      "publishedAt": "2026-04-23T12:53:47Z"
    },
    {
      "videoId": "m13grg6TONw",
      "title": "Thần rừng trở lại Nakroth gánh team sau khi được buff combo choáng cực mạnh",
      "source": "youtube",
      "publishedAt": "2026-04-15T02:30:07Z"
    },
    {
      "videoId": "_9xOp_nFSNk",
      "title": "Cách Flowborn – Tướng Mới Bá Đạo Nhất 2026? Combo 1 Hit Bay Màu!",
      "source": "youtube",
      "publishedAt": "2026-04-09T01:20:29Z"
    },
    {
      "videoId": "5b8uM9TqSw8",
      "title": "Hướng Dẫn Thorne 2026: Combo Đạn Chuẩn – Gánh Team Cực Mạnh!",
      "source": "youtube",
      "publishedAt": "2026-04-07T05:30:20Z"
    },
    {
      "videoId": "ghEVF8qT6Ak",
      "title": "Trùm xạ thủ 2026 gọi tên Best Violet lụm SSS 3 sao cực dễ rank chiến tướng",
      "source": "youtube",
      "publishedAt": "2026-03-27T04:07:25Z"
    },
    {
      "videoId": "hKYEEYkjfb4",
      "title": " HNG DN TNG HP CHUI S KIN L HI 5V5  - Garena Lin Qun Mobile",
      "source": "youtube",
      "publishedAt": "2026-04-28T09:01:23Z"
    },
    {
      "videoId": "m15qM7pknVM",
      "title": "Bonnie Gnh Team Sut 37 Pht Cc Cng, Nak AFK R Rng Nhng Garena Li Lm Ng, Ci Kt G y!?",
      "source": "youtube",
      "publishedAt": "2025-08-06T13:09:16Z"
    },
    {
      "videoId": "FKK-ku52Nwo",
      "title": "VUX LEO RANK CAO TH VI SKIN WISH HNH TRNH K O D ON LY 3 SAO MN NHN",
      "source": "youtube",
      "publishedAt": "2026-04-29T09:49:29Z"
    },
    {
      "videoId": "F9PkxU0xGd8",
      "title": "VUX LEO RANK VỚI TƯỚNG ĐI RỪNG BẰNG 4 TRANG BỊ KHÁC NHAU SAU KHI ĐƯỢC TĂNG SỨC MẠNH",
      "source": "youtube",
      "publishedAt": "2026-04-27T10:10:28Z"
    },
    {
      "videoId": "1uxQ52gqS0M",
      "title": "VUX LEO RANK CAO THỦ VỚI FLOWBORN HỆ PHÁP SƯ CẤU RỈA CỰC KHÓ CHỊU",
      "source": "youtube",
      "publishedAt": "2026-04-25T09:50:09Z"
    },
    {
      "videoId": "7lgmybfTwBI",
      "title": "VUX LEO RANK CAO THỦ VỚI SKIN ARUM CHỊ ĐẠI GANGSTER VÀ ZEPHYS ĐẠI CA GIANG HỒ ĐẦY BÙNG NỔ",
      "source": "youtube",
      "publishedAt": "2026-04-24T09:43:23Z"
    },
    {
      "videoId": "Pimz8WqNNuk",
      "title": "VUX LEO RANK CAO TH VI TT C SKIN ERROL COMBO TAY TO NHT LIN QUN MOBILE",
      "source": "youtube",
      "publishedAt": "2026-04-22T09:27:52Z"
    },
    {
      "videoId": "tvJ260tZcdE",
      "title": "VUX THỬ THÁCH LEO LÊN CAO THỦ VỊ TƯỚNG XUẤT HIỆN ĐẦU TIÊN TRÊN TIKTOK",
      "source": "youtube",
      "publishedAt": "2026-04-21T10:13:16Z"
    },
    {
      "videoId": "z8B88t-d69M",
      "title": "VUX TRỞ THÀNH BẤT TỬ VỚI DEXTRA PHÙ HIỆU ẨN SÁT COMBO LÕI CỰC MẠNH",
      "source": "youtube",
      "publishedAt": "2026-04-20T10:38:40Z"
    },
    {
      "videoId": "ctkju9gjtWc",
      "title": "VUX GỌI ĐIỆN GARENA XIN SKIN NAKROTH THỨ NGUYÊN VỆ THẦN LEO RANK ĐẦY BÙNG NỔ",
      "source": "youtube",
      "publishedAt": "2026-04-16T10:21:01Z"
    },
    {
      "videoId": "DHUM_izAsyY",
      "title": "VUX MỘT NGÀY CHƠI HỖN CHIẾN PHÙ HIỆU CÙNG GIÁO ÁN YORN FULL PHÉP COMBO CHỚP ĐỎ ĐẦY HÀI HƯỚC",
      "source": "youtube",
      "publishedAt": "2026-04-15T09:50:00Z"
    },
    {
      "videoId": "QXWUQ8asisM",
      "title": "VUX LEO TRẬN CUỐI LÊN CAO THỦ VỚI SKIN QUILLEN THẨM PHÁN TRĂNG KHUYẾT BÙNG NỔ",
      "source": "youtube",
      "publishedAt": "2026-04-14T10:45:12Z"
    },
    {
      "videoId": "UkdUycK5i9g",
      "title": "VUX LEO RANK VỚI SKIN BILLOW T-REX BẤT BẠI COMBO GIẢ LẬP MVP GÁNH ĐỒNG ĐỘI",
      "source": "youtube",
      "publishedAt": "2026-04-11T09:02:06Z"
    },
    {
      "videoId": "GBMJWRTX1hc",
      "title": "VUX LEO RANK VỚI SKIN ZILL SIÊU VIỆT VÀ XẠ THỦ MỚI FLOWBORN BẮN CỰC MẠNH",
      "source": "youtube",
      "publishedAt": "2026-04-09T10:00:10Z"
    },
    {
      "videoId": "fkb4JRQZfqc",
      "title": "Nakroth Đang Quá Lỗi Game Trong Meta Này ?",
      "source": "youtube",
      "publishedAt": "2026-04-16T11:15:01Z"
    },
    {
      "videoId": "6PwMn61HOfI",
      "title": "Billow T-Rex Bất Bại Là Một Skin Thất Bại ?",
      "source": "youtube",
      "publishedAt": "2026-04-15T11:15:00Z"
    },
    {
      "videoId": "67ovymusfUI",
      "title": "52 Phút Rank Đơn Cho Những Trận Đấu Lên Rank 97 Sao Của Onekill",
      "source": "youtube",
      "publishedAt": "2026-04-27T10:00:15Z"
    },
    {
      "videoId": "Wa2Z2pBKkcQ",
      "title": "43 Phút Solo Rank Đơn Với Những Trận Đấu Trên Rank 82 Sao Của Onekill",
      "source": "youtube",
      "publishedAt": "2026-04-22T09:54:37Z"
    },
    {
      "videoId": "S2fOvLBzGJY",
      "title": "43 Phút Solo Rank Đơn Cho Hành Trình Leo Thách Đấu Rank 71 Sao Của Onekill",
      "source": "youtube",
      "publishedAt": "2026-04-19T10:15:36Z"
    },
    {
      "videoId": "n-Esd-rMIBU",
      "title": "55 Phút Rank Đơn Với Hành Trình Leo Thách Đấu 62 Sao Của Onekill",
      "source": "youtube",
      "publishedAt": "2026-04-16T10:10:42Z"
    },
    {
      "videoId": "WRQEikkp2Rc",
      "title": "46 Phút Rank Đơn Cho Những Trận Đấu Lên 46 Sao Của Onekill",
      "source": "youtube",
      "publishedAt": "2026-04-13T10:00:47Z"
    },
    {
      "videoId": "3UpQOt46Y-g",
      "title": "45 Phút Rank Đơn Mùa Mới Meta Mới Lên Cao Thủ 28 Sao Của Onekill",
      "source": "youtube",
      "publishedAt": "2026-04-11T10:00:07Z"
    },
    {
      "videoId": "otaHf7J2lEE",
      "title": "47 Phút Rank Đơn Cho Những Trận Đấu Đầu Mùa Lên Cao Thủ Của Onekill",
      "source": "youtube",
      "publishedAt": "2026-04-09T10:49:24Z"
    },
    {
      "videoId": "VukswIKXc40",
      "title": "50 Phút Rank Đơn Cho Những Trận Đấu Cuối Mùa Lên 199 Sao Của Onekill",
      "source": "youtube",
      "publishedAt": "2026-04-07T12:07:55Z"
    },
    {
      "videoId": "b0dwKSHb7IY",
      "title": "57 Phút Cho Những Trận Đấu Cuối Cùng Lên Rank Chiến Thần 190 Sao Của Onekill",
      "source": "youtube",
      "publishedAt": "2026-04-03T10:53:35Z"
    },
    {
      "videoId": "L5ped3_YWRw",
      "title": "30 Phút ( Full Ryoma ) Cho Những Trận Đấu Lên Rank Chiến Thần 180 Sao Của Onekill",
      "source": "youtube",
      "publishedAt": "2026-03-25T09:42:55Z"
    },
    {
      "videoId": "sF1ItyvDu_g",
      "title": "50 Phút Rank Đơn Cho Những Trận Đấu Lên Chiến Thần 170 Sao Của Onekill",
      "source": "youtube",
      "publishedAt": "2026-03-17T10:01:22Z"
    },
    {
      "videoId": "W5U5mXUomu8",
      "title": "56 Phút ( Rank Đơn ) Cho Những Trận Đấu Lên Chiến Thần 168 Sao Của Onekill",
      "source": "youtube",
      "publishedAt": "2026-03-15T10:29:19Z"
    },
    {
      "videoId": "YJlxyrnQm4M",
      "title": "Onekill Vô Tình Đối Đầu Yiwei Và 1S Karl Trên Rank Chiến Thần 15x",
      "source": "youtube",
      "publishedAt": "2026-03-11T10:38:42Z"
    },
    {
      "videoId": "xxgV2sATwvo",
      "title": "50 Phút ( Rank Đơn ) Leo Thách Đấu Cho Những Trận Đấu Lên 157 Sao Của Onekill",
      "source": "youtube",
      "publishedAt": "2026-03-08T10:01:26Z"
    }
  ]
}