{
  "videos": [
    {
      "videoId": "Nh_zacl9YsE",
      "title": "RoV Tier List จัดอันดับฮีโร่โซโล่แรงก์โดย Erez",
      "source": "youtube",
      "publishedAt": "2026-02-03T05:31:00Z"
    },
    {
      "videoId": "5AHD-W6lZvE",
      "title": "การแข่งขัน RoV Pro League 2026 Summer | รอบเก็บคะแนน Week 1 Day 2",
      "source": "youtube",
      "publishedAt": "2026-02-01T15:20:26Z"
    },
    {
      "videoId": "xmL6Q2Qa-o0",
      "title": "เปิดสนามวันแรก RoV Pro League 2026 Summer | รอบเก็บคะแนน Week 1 Day 1",
      "source": "youtube",
      "publishedAt": "2026-01-31T14:15:54Z"
    },
    {
      "videoId": "dRZrhQlCBLA",
      "title": "  CHIA S T NH PHT TRIN | THAY I LI CHI BN CP NHT MI  - Garena Lin Qun Mobile",
      "source": "youtube",
      "publishedAt": "2026-01-26T07:00:27Z"
    },
    {
      "videoId": "m15qM7pknVM",
      "title": "Bonnie Gnh Team Sut 37 Pht Cc Cng, Nak AFK R Rng Nhng Garena Li Lm Ng, Ci Kt G y!?",
      "source": "youtube",
      "publishedAt": "2025-08-06T13:09:16Z"
    },
    {
      "videoId": "Lye0Dd4xP7Y",
      "title": "一起聽別單機 EP9 | 大哥們有話要說，戰隊新成員即將降臨？！ft. ONE TURA、ONE JUNNN 《Garena傳說對決》",
      "source": "youtube",
      "publishedAt": "2026-01-31T04:00:31Z"
    },
    {
      "videoId": "AaMDsaLXsLI",
      "title": "【直播精華】Dwei不藏私打野教學!直呼這個套路無解，只能靠隊友支援💪 《Garena 傳說對決》",
      "source": "youtube",
      "publishedAt": "2026-01-30T12:30:24Z"
    },
    {
      "videoId": "i1TTc1RJ2Tk",
      "title": "【策劃面對面】創新紀元版本 - 機制調整《Garena 傳說對決》",
      "source": "youtube",
      "publishedAt": "2026-01-27T12:01:17Z"
    },
    {
      "videoId": "r3nZFAh2raU",
      "title": "【策劃面對面】創新紀元版本 - 英雄平衡改動《Garena 傳說對決》",
      "source": "youtube",
      "publishedAt": "2026-01-26T14:26:25Z"
    },
    {
      "videoId": "wi-E9TuRcrw",
      "title": "Skin Showcase - Miracle-prone: Teng Snake | Arena of Valor",
      "source": "youtube",
      "publishedAt": "2026-01-23T10:01:34Z"
    },
    {
      "videoId": "SoFj1MIlWRY",
      "title": "Codex Showcase - Cyborg Vagabond | Arena of Valor",
      "source": "youtube",
      "publishedAt": "2026-01-09T11:00:55Z"
    },
    {
      "videoId": "OtwSQH07LEE",
      "title": "Get Bijan's New Christmas Skin for Free | Arena of Valor",
      "source": "youtube",
      "publishedAt": "2025-12-12T13:15:09Z"
    },
    {
      "videoId": "fRqTMj6rJds",
      "title": "Veres-S Dreamer skin spotlight",
      "source": "youtube",
      "publishedAt": "2022-11-02T06:38:16Z"
    },
    {
      "videoId": "jhk5Mb8xpcE",
      "title": "Allain-Wolfling Volant skin spotlight",
      "source": "youtube",
      "publishedAt": "2022-11-02T06:38:01Z"
    },
    {
      "videoId": "Km7e-Tokd7c",
      "title": "Alice-Astro Odyssey skin spotlight",
      "source": "youtube",
      "publishedAt": "2022-11-02T06:31:50Z"
    },
    {
      "videoId": "sLQnN8nNdbA",
      "title": "Caphney-Wedding Day skin spotlight",
      "source": "youtube",
      "publishedAt": "2022-11-02T06:29:55Z"
    },
    {
      "videoId": "2cuhh-pZxzw",
      "title": "Xeniel-Demonic Creation skin spotlight",
      "source": "youtube",
      "publishedAt": "2022-08-24T02:49:58Z"
    },
    {
      "videoId": "y4SyyPdyAWQ",
      "title": "Yue Chaos Sovereign Skin Spotlight - Garena AOV Indonesia #arenaofvalor",
      "source": "youtube",
      "publishedAt": "2026-01-28T07:32:33Z"
    },
    {
      "videoId": "MzEFbVto5gc",
      "title": "Cinnamoroll's Dream Aya Skin Spotlight - Garena AOV Indonesia #Sanriocharacters #arenaofvalor",
      "source": "youtube",
      "publishedAt": "2026-01-01T03:09:05Z"
    },
    {
      "videoId": "olqkhmaSjuo",
      "title": "Chaugnar Pixel Storm Skin Spotlight - Garena AOV Indonesia #arenaofvalor #codexs84",
      "source": "youtube",
      "publishedAt": "2025-12-31T07:53:00Z"
    },
    {
      "videoId": "T_5hNV8-W8A",
      "title": "AOV Masters × Dev Team – 10th Anniversary Special Edition #arenaofvalor",
      "source": "youtube",
      "publishedAt": "2025-12-31T02:38:41Z"
    },
    {
      "videoId": "qetyoUnsbZw",
      "title": "Cinnamoroll's Dream Aya - Garena AOV Indonesia",
      "source": "youtube",
      "publishedAt": "2025-12-29T10:01:40Z"
    },
    {
      "videoId": "8Ka5laFgS4Q",
      "title": "Kuromi's Heart Natalya - Garena AOV Indonesia #Sanriocharacters #arenaofvalor",
      "source": "youtube",
      "publishedAt": "2025-12-29T03:35:30Z"
    },
    {
      "videoId": "7sAyHkOgmRY",
      "title": "My Melody's Love Veera Skin Spotlight - Garena AOV Indonesia #Sanriocharacters #arenaofvalor",
      "source": "youtube",
      "publishedAt": "2025-12-23T10:00:12Z"
    },
    {
      "videoId": "_jAAvaTEChU",
      "title": "Grand Finals AOV Mendadak Tourney 2025 - Garena AOV Indonesia!",
      "source": "youtube",
      "publishedAt": "2025-12-21T13:42:46Z"
    },
    {
      "videoId": "5N53248JkrY",
      "title": "Moren Revamp Hero Spotlight - Garena AOV Indonesia",
      "source": "youtube",
      "publishedAt": "2025-12-18T04:22:51Z"
    },
    {
      "videoId": "R4r-GNWdM_o",
      "title": "PomPomPurin's Oath Arthur Skin Spotlight - Garena AOV Indonesia #Sanriocharacters #arenaofvalor",
      "source": "youtube",
      "publishedAt": "2025-12-17T04:30:23Z"
    },
    {
      "videoId": "FQrR9k52QaQ",
      "title": "Kuromi's Heart Natalya Skin Spotlight - Garena AOV Indonesia #Sanriocharacters #arenaofvalor",
      "source": "youtube",
      "publishedAt": "2025-12-16T05:07:23Z"
    },
    {
      "videoId": "mEpPLNsZJJE",
      "title": "Grand Finals AIC 2025 | Garena AOV Indonesia",
      "source": "youtube",
      "publishedAt": "2025-12-07T15:38:54Z"
    },
    {
      "videoId": "XeXiDggHGG4",
      "title": "Semi Finals AIC 2025 | Garena AOV Indonesia",
      "source": "youtube",
      "publishedAt": "2025-12-06T13:40:30Z"
    },
    {
      "videoId": "N2ilP7VgO3I",
      "title": "Veres Snowwish Skin Spotlight - Garena AOV Indonesia #arenaofvalor",
      "source": "youtube",
      "publishedAt": "2025-12-01T13:00:55Z"
    },
    {
      "videoId": "AkkCoHMIa-M",
      "title": "AOV : ELSU GAMEPLAY | BUILD DPS - ARENA OF VALOR LIENQUANMOBILE ROV",
      "source": "youtube",
      "publishedAt": "2026-02-02T15:00:18Z"
    },
    {
      "videoId": "Wlq0KHA7O8Y",
      "title": "AOV : WUKONG GAMEPLAY | HARD GAME - ARENA OF VALOR LIENQUANMOBILE ROV",
      "source": "youtube",
      "publishedAt": "2026-02-01T15:01:01Z"
    },
    {
      "videoId": "Rbu5k1Cdxd4",
      "title": "AOV : TULEN/GOJO GAMEPLAY | INSANE DAMAGE - ARENA OF VALOR LIENQUANMOBILE ROV",
      "source": "youtube",
      "publishedAt": "2026-01-31T15:00:59Z"
    },
    {
      "videoId": "GyC5h73MbpM",
      "title": "AOV : NEW SKIN TACHI SCORPIO GAMEPLAY - ARENA OF VALOR LIENQUANMOBILE ROV",
      "source": "youtube",
      "publishedAt": "2026-01-30T15:00:37Z"
    },
    {
      "videoId": "et-54A5cJLk",
      "title": "AOV : MURAD/ZENITSU GAMEPLAY | AT TARGET QUILLEN - ARENA OF VALOR LIENQUANMOBILE ROV",
      "source": "youtube",
      "publishedAt": "2026-01-29T15:01:12Z"
    },
    {
      "videoId": "NH8RFDe6e-E",
      "title": "AOV : NEW SKIN YUE CHAOS SOVEREIGN GAMEPLAY - ARENA OF VALOR LIENQUANMOBILE ROV",
      "source": "youtube",
      "publishedAt": "2026-01-28T12:31:19Z"
    },
    {
      "videoId": "o9pMNPSVsmw",
      "title": "AOV : CHARLOTTE GAMEPLAY | VS YENA - ARENA OF VALOR LIENQUANMOBILE ROV",
      "source": "youtube",
      "publishedAt": "2026-01-28T01:14:25Z"
    },
    {
      "videoId": "9IXLtnfQN00",
      "title": "AOV : BOLT BARON GAMEPLAY | IN JUNGLE - ARENA OF VALOR LIENQUANMOBILE ROV",
      "source": "youtube",
      "publishedAt": "2026-01-26T15:00:23Z"
    },
    {
      "videoId": "dPJwj68gRco",
      "title": "AOV : TULEN/GOJO GAMEPLAY | IN JUNGLE - ARENA OF VALOR LIENQUANMOBILE ROV",
      "source": "youtube",
      "publishedAt": "2026-01-25T15:01:08Z"
    },
    {
      "videoId": "CQJScf-2kJ8",
      "title": "AOV : ROURKE GAMEPLAY | IN JUNGLE - ARENA OF VALOR LIENQUANMOBILE ROV",
      "source": "youtube",
      "publishedAt": "2026-01-24T15:00:15Z"
    },
    {
      "videoId": "wi_59sZowJs",
      "title": "AOV : ISHAR BUFFED NEW PATCH - ARENA OF VALOR LIENQUANMOBILE ROV",
      "source": "youtube",
      "publishedAt": "2026-01-23T15:01:48Z"
    },
    {
      "videoId": "pyocfN-4RFI",
      "title": "【アリヴァラ公式生放送】-AoV闘龍門Z- 第5回",
      "source": "youtube",
      "publishedAt": "2022-04-30T13:27:35Z"
    },
    {
      "videoId": "TacvmjlGMio",
      "title": "【アリヴァラ公式生放送】-AoV闘龍門Z- 第4回",
      "source": "youtube",
      "publishedAt": "2022-03-26T13:12:05Z"
    },
    {
      "videoId": "Kolwstb2l2I",
      "title": "【アリヴァラ公式生放送】-AoV闘龍門Z- 第3回",
      "source": "youtube",
      "publishedAt": "2022-02-26T12:15:48Z"
    },
    {
      "videoId": "bKF_ap6ZRmA",
      "title": "【アリヴァラ公式生放送】-AoV闘龍門Z- 第2回",
      "source": "youtube",
      "publishedAt": "2022-01-29T12:39:28Z"
    },
    {
      "videoId": "g48BB884JGM",
      "title": "【アリヴァラ公式生放送】-AoV闘龍門Z-  第1回",
      "source": "youtube",
      "publishedAt": "2021-12-19T14:05:39Z"
    },
    {
      "videoId": "_phDFQbcaLw",
      "title": "HIỆU ỨNG TRANG PHỤC BILLOW - THIÊN TƯỚNG ĐỘ ÁCH  ( FULL HD )",
      "source": "youtube",
      "publishedAt": "2026-02-02T15:43:36Z"
    },
    {
      "videoId": "spC4kYGhErI",
      "title": "FULL SPLASH ART TEERI LUNAR NEW YEAR 2026 - Arena of Valor",
      "source": "youtube",
      "publishedAt": "2026-02-01T06:08:51Z"
    },
    {
      "videoId": "TuEOzQX2VvU",
      "title": "Skin Önizlemesi - Miracle-prone: Teng Snake | Arena of Valor",
      "source": "youtube",
      "publishedAt": "2026-01-23T10:00:49Z"
    },
    {
      "videoId": "TMQV8BQijRA",
      "title": "Codex Sergisi - Cyborg Vagabond | Arena of Valor",
      "source": "youtube",
      "publishedAt": "2026-01-09T11:01:03Z"
    },
    {
      "videoId": "RDBh-ZNpSGM",
      "title": "Noel Hediye Etkinliği'ne Katıl | Arena of Valor",
      "source": "youtube",
      "publishedAt": "2025-12-29T05:04:12Z"
    },
    {
      "videoId": "HdYoywke8Ww",
      "title": "Bijan'ın Yeni Noel Görünümünü Ücretsiz Edinin | Arena of Valor",
      "source": "youtube",
      "publishedAt": "2025-12-12T13:15:02Z"
    },
    {
      "videoId": "MDmoFK7mqSU",
      "title": "VP41 CODEX Sezonu Trailer I Arena of Valor Yeni Çağ",
      "source": "youtube",
      "publishedAt": "2023-02-26T13:30:07Z"
    },
    {
      "videoId": "NDiQkWX1f30",
      "title": "VP40 CODEX Trailer I Arena of Valor Yeni Çağ",
      "source": "youtube",
      "publishedAt": "2022-12-26T21:00:08Z"
    },
    {
      "videoId": "nzpHtZFGF9g",
      "title": "Sezon 38 Hacker Codex Arena of Valor'da!",
      "source": "youtube",
      "publishedAt": "2022-09-05T10:02:16Z"
    },
    {
      "videoId": "69ydJHcW5E0",
      "title": "Diaochan Terzi Arena'da! | AoV Kostüm Tanıtımı",
      "source": "youtube",
      "publishedAt": "2022-07-18T09:31:52Z"
    },
    {
      "videoId": "mFgvTHucJwk",
      "title": "AoV Günü Müzik Parkuru Butterfly Performansı ile Başlıyor!",
      "source": "youtube",
      "publishedAt": "2022-07-16T11:58:26Z"
    },
    {
      "videoId": "Ctf9Jk8F6i4",
      "title": "Arena Of Valor : Lobby Soundtrack【Patch 1.61】#2026  #arenaofvalor",
      "source": "youtube",
      "publishedAt": "2026-01-21T06:56:06Z"
    },
    {
      "videoId": "Byins9sxP-k",
      "title": "Arena Of Valor X Sanrio Characters : Lobby Soundtrack  [Patch 1.60.1.10] #anwsoundtrack",
      "source": "youtube",
      "publishedAt": "2025-12-27T03:00:16Z"
    },
    {
      "videoId": "-ryv96dCbrA",
      "title": "Arena Of Valor : Lobby Soundtrack (Tossakan : Maloch)【Patch 1.60.1.8】#rovthailand",
      "source": "youtube",
      "publishedAt": "2025-11-29T03:39:11Z"
    },
    {
      "videoId": "BuQ8Z8YhDQA",
      "title": "Arena Of Valor x That Time I Got Reincarnated as a Slime : Lobby Soundtrack [Patch 1.60]",
      "source": "youtube",
      "publishedAt": "2025-11-08T03:57:58Z"
    },
    {
      "videoId": "aSMlFxYPRw4",
      "title": "Arena Of Valor : Eland'orr「DREAMLINER」Lobby Soundtrack #arenaofvalor",
      "source": "youtube",
      "publishedAt": "2025-10-25T03:00:01Z"
    },
    {
      "videoId": "4ccO3c3dzoE",
      "title": "Arena Of Valor : 9th Anniversary : 「DREAMLINER」 Soundtrack #2025 #arenaofvalor",
      "source": "youtube",
      "publishedAt": "2025-10-22T08:15:19Z"
    },
    {
      "videoId": "pWLpXgiuFVI",
      "title": "Arena Of Valor : Lobby Soundtrack (Azzen'Ka Rework)【Patch 1.60】#2025 #arenaofvalor",
      "source": "youtube",
      "publishedAt": "2025-10-22T04:44:23Z"
    },
    {
      "videoId": "ztv923XLhnY",
      "title": "Arena Of Valor X Detective Conan : Lobby Soundtrack  [Patch 1.59.1.7] #anwsoundtrack",
      "source": "youtube",
      "publishedAt": "2025-08-15T09:51:34Z"
    },
    {
      "videoId": "NXMpnkMCLZ0",
      "title": "Arena Of Valor : Super July Lobby Soundtrack【Patch 1.59】#2025 #rovthailand",
      "source": "youtube",
      "publishedAt": "2025-07-15T06:10:09Z"
    },
    {
      "videoId": "Xiz2WURsWis",
      "title": "Arena Of Valor : Valentine 2025 Lobby Soundtrack【Patch 1.57】#2025 #rovthailand",
      "source": "youtube",
      "publishedAt": "2025-02-09T05:23:51Z"
    },
    {
      "videoId": "sEFeNjxtUog",
      "title": "Arena Of Valor : Lunar New Year 2025 Soundtrack (\"Capheny\")【Patch 1.57】#2025  #rovthailand",
      "source": "youtube",
      "publishedAt": "2025-01-27T04:35:54Z"
    },
    {
      "videoId": "1TBrPwx32VQ",
      "title": "Arena Of Valor : Lobby Soundtrack (\"Billow\")【Patch 1.57】#2025  #rovthailand",
      "source": "youtube",
      "publishedAt": "2025-01-10T09:42:07Z"
    },
    {
      "videoId": "gsEqCILSPiE",
      "title": "Arena Of Valor X Jujutsu Kaisen : Lobby Soundtrack  [Patch 1.56.1] #garenarovthailand",
      "source": "youtube",
      "publishedAt": "2024-11-02T06:37:08Z"
    },
    {
      "videoId": "L07yi7dm2VY",
      "title": "Arena Of Valor : Lobby Soundtrack (\"Biron\")【Patch 1.56.1】#2024 #rovthailand",
      "source": "youtube",
      "publishedAt": "2024-10-10T05:01:40Z"
    },
    {
      "videoId": "VSwtTcZwYiE",
      "title": "Arena Of Valor : Lobby Soundtrack (Y'bneth : Prate \"ผีเปรต\")【Patch 1.55.1.9】#2024 #rovthailand",
      "source": "youtube",
      "publishedAt": "2024-09-06T08:37:22Z"
    },
    {
      "videoId": "rs7WDh9fnEM",
      "title": "Skin Showcase - Miracle-prone: Teng Snake | Arena of Valor",
      "source": "youtube",
      "publishedAt": "2026-01-23T10:01:19Z"
    },
    {
      "videoId": "9Wq88BLn5iY",
      "title": "Codex Showcase - Cyborg Vagabond | Arena of Valor",
      "source": "youtube",
      "publishedAt": "2026-01-09T11:00:15Z"
    },
    {
      "videoId": "ucIgkso7HXE",
      "title": "Get Bijan's New Christmas Skin For Free | Arena of Valor",
      "source": "youtube",
      "publishedAt": "2025-12-12T13:15:08Z"
    },
    {
      "videoId": "dMgefTpLUbc",
      "title": "Codex Season 40 | Arena of Valor",
      "source": "youtube",
      "publishedAt": "2022-12-26T08:45:00Z"
    },
    {
      "videoId": "ZP8ZSECGGgI",
      "title": "নতুন স্কিন । Veres-S Dreamer Skin Spotlight",
      "source": "youtube",
      "publishedAt": "2022-10-19T08:00:13Z"
    },
    {
      "videoId": "_BaqrFBjn9Y",
      "title": "নতুন স্কিন । Allain-Wolfling Volant Skin Spotlight",
      "source": "youtube",
      "publishedAt": "2022-10-17T06:00:17Z"
    },
    {
      "videoId": "mr5MNLXMwu0",
      "title": "নতুন স্কিন । Alice-Astro Odyssey skin spotlight",
      "source": "youtube",
      "publishedAt": "2022-10-02T06:00:22Z"
    },
    {
      "videoId": "jk6ulUy4Mdw",
      "title": "নতুন স্কিন । Caphney-Wedding Day skin spotlight",
      "source": "youtube",
      "publishedAt": "2022-10-01T12:00:33Z"
    },
    {
      "videoId": "AkVd6tf52FU",
      "title": "নতুন স্কিন | Xeniel-Demonic Creation Skin Spotlight",
      "source": "youtube",
      "publishedAt": "2022-08-12T09:00:06Z"
    },
    {
      "videoId": "noWgoy5VvBE",
      "title": "[BENGALI] GRAND FINALS || AOV COMMUNITY CUP || GRAMEENPHONE",
      "source": "youtube",
      "publishedAt": "2022-07-29T14:55:00Z"
    },
    {
      "videoId": "T1gA0vGdYMo",
      "title": "[BENGALI] GRAND FINALS || AOV COMMUNITY CUP || GRAMEENPHONE",
      "source": "youtube",
      "publishedAt": "2022-07-29T14:37:30Z"
    },
    {
      "videoId": "apUU0EWoTeA",
      "title": "Codex da Temporada 39 | Arena of Valor BR",
      "source": "youtube",
      "publishedAt": "2022-10-29T22:00:00Z"
    },
    {
      "videoId": "bjrbg20Kdlc",
      "title": "Alice - Odisseia Astral | Arena of Valor BR",
      "source": "youtube",
      "publishedAt": "2022-10-15T22:00:14Z"
    },
    {
      "videoId": "iZTALUBD4FM",
      "title": "Teeri chega ao Campo de Batalha | Arena of Valor BR",
      "source": "youtube",
      "publishedAt": "2022-09-29T22:00:17Z"
    },
    {
      "videoId": "o8GDkk49PTk",
      "title": "Codex da Temporada 38 - Hacker | Arena of Valor BR",
      "source": "youtube",
      "publishedAt": "2022-09-06T22:00:31Z"
    },
    {
      "videoId": "ULaz5q0zopg",
      "title": "Skin Spotlight - Xeniel Criação Demoníaca | Arena of Valor BR",
      "source": "youtube",
      "publishedAt": "2022-08-12T21:41:09Z"
    },
    {
      "videoId": "zZMriqDlVYc",
      "title": "Música Tema - Explorador de Dimensões | Arena of Valor BR",
      "source": "youtube",
      "publishedAt": "2022-07-23T23:00:30Z"
    },
    {
      "videoId": "j-3Bkgl6On0",
      "title": "Exploradores de Dimensões | Arena of Valor BR",
      "source": "youtube",
      "publishedAt": "2022-07-22T22:00:30Z"
    },
    {
      "videoId": "Tjm8am4M4_4",
      "title": "Festival de Música do Dia do AoV | Arena of Valor BR",
      "source": "youtube",
      "publishedAt": "2022-07-17T21:00:10Z"
    },
    {
      "videoId": "_KEQY_S04IM",
      "title": "Skin Spotlight Diaochan - Costureira | Arena of Valor BR",
      "source": "youtube",
      "publishedAt": "2022-07-16T20:00:08Z"
    },
    {
      "videoId": "df-pAZr51r0",
      "title": "Iggy - Assombração Felina | Arena of Valor BR",
      "source": "youtube",
      "publishedAt": "2022-07-13T22:00:30Z"
    },
    {
      "videoId": "aM7m4oxtWO4",
      "title": "Valor Pass 37 - Parada Youkai | Arena of Valor BR",
      "source": "youtube",
      "publishedAt": "2022-06-28T22:19:50Z"
    },
    {
      "videoId": "jA-SW6SHPCg",
      "title": "EU Region Highlights - Valor Series Season 3 Week 8",
      "source": "youtube",
      "publishedAt": "2019-04-01T18:28:18Z"
    },
    {
      "videoId": "irdOYsHyJxw",
      "title": "LATAM Region Highlights - Valor Series Season 3 Week 8",
      "source": "youtube",
      "publishedAt": "2019-04-01T18:28:16Z"
    },
    {
      "videoId": "9_A0fAjyUOc",
      "title": "NA Region Highlights - Valor Series Season 3 Week 8",
      "source": "youtube",
      "publishedAt": "2019-04-01T18:28:14Z"
    },
    {
      "videoId": "4bcQfuV1fHo",
      "title": "الضوء والظل - الفصل السادس: الليل القرمزي | أرينا أوف فالور | Arena of Valor | TiMi",
      "source": "youtube",
      "publishedAt": "2022-07-17T12:09:28Z"
    },
    {
      "videoId": "CAURoEPs5n0",
      "title": "الضوء والظل - الفصل الخامس: البوابة | أرينا أوف فالور | Arena of Valor | TiMi",
      "source": "youtube",
      "publishedAt": "2022-06-25T10:00:50Z"
    },
    {
      "videoId": "YcQ-mRDWrbE",
      "title": "Arena of Valor - Hero Breakdown - Episode 11: Mina",
      "source": "youtube",
      "publishedAt": "2018-06-12T14:59:32Z"
    },
    {
      "videoId": "aqbpWYKn-6o",
      "title": "[Türk] Arena of Valor - Hero Breakdown - Bölüm 11: Mina",
      "source": "youtube",
      "publishedAt": "2018-06-12T14:59:32Z"
    },
    {
      "videoId": "urSFbcVa7Sc",
      "title": "[Deutsch] Arena Of Valor - Hero Breakdown - Episode 11: Mina",
      "source": "youtube",
      "publishedAt": "2018-06-12T14:59:32Z"
    },
    {
      "videoId": "CrmXhOuLLuQ",
      "title": "[Español] Arena Of Valor - Hero Breakdown - Episodio 11: Mina",
      "source": "youtube",
      "publishedAt": "2018-06-12T14:59:31Z"
    },
    {
      "videoId": "iL4P7Ob0mZo",
      "title": "[Français] Arena Of Valor - Hero Breakdown - Episode 11: Mina",
      "source": "youtube",
      "publishedAt": "2018-06-12T14:59:31Z"
    },
    {
      "videoId": "cc0SR-lyK-Y",
      "title": "[Deutsch] Arena Of Valor - Hero Breakdown - Episode 10: Taara",
      "source": "youtube",
      "publishedAt": "2018-05-24T18:25:15Z"
    },
    {
      "videoId": "p26E7qrqo2Y",
      "title": "Arena of Valor - Hero Breakdown - Episode 10: Taara",
      "source": "youtube",
      "publishedAt": "2018-05-24T18:25:15Z"
    },
    {
      "videoId": "V_BdVGTsdv8",
      "title": "[Türk] Arena of Valor - Hero Breakdown - Bölüm 10: Taara",
      "source": "youtube",
      "publishedAt": "2018-05-24T18:25:14Z"
    },
    {
      "videoId": "g0KSLLbDGDQ",
      "title": "[Español] Arena Of Valor - Hero Breakdown - Episodio 10: Taara",
      "source": "youtube",
      "publishedAt": "2018-05-24T18:25:14Z"
    },
    {
      "videoId": "yGwXgLIFStc",
      "title": "[Français] Arena Of Valor - Hero Breakdown - Episode 10: Taara",
      "source": "youtube",
      "publishedAt": "2018-05-24T18:25:14Z"
    },
    {
      "videoId": "MFT0FOPdBug",
      "title": "[Deutsch] Arena Of Valor - Hero Breakdown - Episode 9: Aleister",
      "source": "youtube",
      "publishedAt": "2018-05-10T08:15:39Z"
    },
    {
      "videoId": "bPy8TXp_3Y8",
      "title": "Arena of Valor - Hero Breakdown - Episode 9: Aleister",
      "source": "youtube",
      "publishedAt": "2018-05-08T18:54:13Z"
    },
    {
      "videoId": "I-iwtVCX1Qs",
      "title": "[Español] Arena Of Valor - Hero Breakdown - Episodio 9: Aleister",
      "source": "youtube",
      "publishedAt": "2018-05-08T18:54:12Z"
    },
    {
      "videoId": "eoo6FKqlMV4",
      "title": "[Français] Arena Of Valor - Hero Breakdown - Episode 9: Aleister",
      "source": "youtube",
      "publishedAt": "2018-05-08T18:54:12Z"
    },
    {
      "videoId": "fphNuKPrxWA",
      "title": "[Türk] Arena of Valor - Hero Breakdown - Bölüm 9: Aleister",
      "source": "youtube",
      "publishedAt": "2018-05-08T18:54:12Z"
    },
    {
      "videoId": "J3HT1uDqw2A",
      "title": "Skin Showcase - Miracle-prone: Teng Snake | Arena of Valor",
      "source": "youtube",
      "publishedAt": "2026-01-23T10:00:23Z"
    },
    {
      "videoId": "Q76j_-QYMuw",
      "title": "Codex Showcase - Cyborg Vagabond | Arena of Valor",
      "source": "youtube",
      "publishedAt": "2026-01-09T11:01:01Z"
    },
    {
      "videoId": "_Tw03fakAWo",
      "title": "Get Bijan's New Christmas Skin For Free | Arena of Valor",
      "source": "youtube",
      "publishedAt": "2025-12-12T13:15:04Z"
    }
  ]
}