{
  "videos": [
    {
      "videoId": "4gp6yEAPH3o",
      "title": "Cch Best iu Thuyn cm Skin Xn nht game lin qun Nht Nguyt thnh linh bn hnh team bn",
      "source": "youtube",
      "publishedAt": "2026-02-16T11:12:42Z"
    },
    {
      "videoId": "W63BCHY_JqY",
      "title": "Phong cách khiến Moren bị cấm trong rank cực nhiều hóa quái vật từ phế vật",
      "source": "youtube",
      "publishedAt": "2026-02-01T12:12:44Z"
    },
    {
      "videoId": "Wi_thyhLYKM",
      "title": "Tướng mạnh mà ít người chơi Ishar và cách ép team địch 7 phút GG luôn",
      "source": "youtube",
      "publishedAt": "2026-01-30T05:03:49Z"
    },
    {
      "videoId": "uVGy-DR9AC8",
      "title": "Tướng mới Moren nhảy nhót bay như chim cả trận, Rank đầu mùa có nên chơi k",
      "source": "youtube",
      "publishedAt": "2026-01-21T08:33:43Z"
    },
    {
      "videoId": "ZoRnuFhnVOg",
      "title": "การแข่งขัน RoV Pro League 2026 Summer | รอบเก็บคะแนน Week 7 Day 4",
      "source": "youtube",
      "publishedAt": "2026-03-15T14:07:22Z"
    },
    {
      "videoId": "gdytWPJUUqA",
      "title": "[Gcaothu] Chê tướng đời đầu phế vật không ai chơi - Mganga cho địch nếm đủ mùi thua cay đắng",
      "source": "youtube",
      "publishedAt": "2026-02-26T09:54:07Z"
    },
    {
      "videoId": "cc8EbICQd2o",
      "title": "[Gcaothu] Con tướng solo mạnh nhất 2026 ít người chơi - Hành Murad ra bã lên là chết phải xóa game",
      "source": "youtube",
      "publishedAt": "2026-02-25T10:52:35Z"
    },
    {
      "videoId": "zw4GjVv_Nfc",
      "title": "Ti Leo Rank THCH U Bng TNG Di y X HI",
      "source": "youtube",
      "publishedAt": "2026-03-10T12:00:16Z"
    },
    {
      "videoId": "FyLxaQk-ZtU",
      "title": "Cách Rank CAO THỦ Vài Sao !",
      "source": "youtube",
      "publishedAt": "2026-03-10T06:57:55Z"
    },
    {
      "videoId": "G9qDkkDxwz4",
      "title": "Lin Qun Top 5 Tng X Th Mnh Nht Meta TDV 2026, TNG",
      "source": "youtube",
      "publishedAt": "2026-03-16T03:00:18Z"
    },
    {
      "videoId": "ot1qZzPt_Qk",
      "title": "Lin Qun Top 5 Tng Solo Lane Mnh Nht Meta TDV 2026, TNG",
      "source": "youtube",
      "publishedAt": "2026-03-15T03:29:14Z"
    },
    {
      "videoId": "Q7fLKHEEVnc",
      "title": "Lin Qun Top 5 Tng i Rng Mnh Nht Meta TDV 2026, TNG",
      "source": "youtube",
      "publishedAt": "2026-03-14T03:00:25Z"
    },
    {
      "videoId": "iqZxezGAlFI",
      "title": "Lin Qun Top 5 Tng Khc Ch NATALYA, Hot Rank Ma S1 2026",
      "source": "youtube",
      "publishedAt": "2026-03-11T03:00:56Z"
    },
    {
      "videoId": "V34_RW8p3vI",
      "title": "Lin Qun _ Nak Qu Thng Quy Rank u Ma B ng i Xem Thng V Ci Kt",
      "source": "youtube",
      "publishedAt": "2026-01-24T03:00:37Z"
    },
    {
      "videoId": "WJTfS6FA9mA",
      "title": "Lin Qun _ Thnh Raz Ti Xut  Pho No Lm Pht  | 1 Combo 2 Mng L C Tht",
      "source": "youtube",
      "publishedAt": "2025-11-14T03:00:30Z"
    },
    {
      "videoId": "x36eUEt6nAM",
      "title": "Lin Qun _ Tng Ma Nak Rank 3x Ngon Lnh V Ci Kt Tht i Di i Lun",
      "source": "youtube",
      "publishedAt": "2025-10-14T03:57:54Z"
    },
    {
      "videoId": "Z0N2GkJNCqs",
      "title": "Lin Qun _ My B G Ny 1 Combo L Bc Hi | Paine C Ny Team Bn Sao Chu Ni",
      "source": "youtube",
      "publishedAt": "2025-10-10T03:28:03Z"
    },
    {
      "videoId": "qvF5m4JHA7Q",
      "title": " HIU NG CHIU THC | KRIXI KIMONO  - Garena Lin Qun Mobile",
      "source": "youtube",
      "publishedAt": "2026-03-12T05:00:47Z"
    },
    {
      "videoId": "EbGSBtCYamM",
      "title": " MN HNH CHN TNG | KRIXI KIMONO  - Garena Lin Qun Mobile",
      "source": "youtube",
      "publishedAt": "2026-03-11T05:00:25Z"
    },
    {
      "videoId": "m15qM7pknVM",
      "title": "Bonnie Gnh Team Sut 37 Pht Cc Cng, Nak AFK R Rng Nhng Garena Li Lm Ng, Ci Kt G y!?",
      "source": "youtube",
      "publishedAt": "2025-08-06T13:09:16Z"
    },
    {
      "videoId": "5MpuFFqqiyA",
      "title": "【對戰精華】ANK vs BMG，ANK LONG 莉莉安團戰%傷直接咬死 BMG 雙C，BMG 你家主堡失火啦🔥《Garena 傳說對決》",
      "source": "youtube",
      "publishedAt": "2026-03-15T15:06:51Z"
    },
    {
      "videoId": "6JfjgDBdjbU",
      "title": "GCS 2026 春季例行賽W3D3－2026/03/15《Garena 傳說對決》",
      "source": "youtube",
      "publishedAt": "2026-03-15T14:10:58Z"
    },
    {
      "videoId": "mtyESYBwh_0",
      "title": "【對戰精華】HKA vs ONE，FONG 弗洛倫二塔遊龍直接把 WULIU 的卡芬妮當成陀螺抽，這就是最強弗洛倫🔥《Garena 傳說對決》",
      "source": "youtube",
      "publishedAt": "2026-03-15T11:24:34Z"
    },
    {
      "videoId": "kgo6CaLvmpU",
      "title": "【對戰精華】FW vs DCG，又是打好打滿！FW NAILIU 與 YUXIANG 至尊雙邊凱撒池直接出手，這就是狼王的宰制力！《Garena 傳說對決》",
      "source": "youtube",
      "publishedAt": "2026-03-14T15:32:34Z"
    },
    {
      "videoId": "k7UFj9hGNsk",
      "title": "GCS 2026 春季例行賽W3D2－2026/03/14《Garena 傳說對決》",
      "source": "youtube",
      "publishedAt": "2026-03-14T14:31:29Z"
    },
    {
      "videoId": "j_---HQlglo",
      "title": "【對戰精華】BMG vs LIT，BMG WANYI 中路神明令月輸出直接爆表48%，直接爆叉 LIT 整場🔥《Garena 傳說對決》",
      "source": "youtube",
      "publishedAt": "2026-03-14T12:17:34Z"
    },
    {
      "videoId": "5LGyPCUfOxU",
      "title": "Skin Showcase - Divine Steed | Arena of Valor",
      "source": "youtube",
      "publishedAt": "2026-03-16T10:00:14Z"
    },
    {
      "videoId": "wi-E9TuRcrw",
      "title": "Skin Showcase - Miracle-prone: Teng Snake | Arena of Valor",
      "source": "youtube",
      "publishedAt": "2026-01-23T10:01:34Z"
    },
    {
      "videoId": "SoFj1MIlWRY",
      "title": "Codex Showcase - Cyborg Vagabond | Arena of Valor",
      "source": "youtube",
      "publishedAt": "2026-01-09T11:00:55Z"
    },
    {
      "videoId": "OtwSQH07LEE",
      "title": "Get Bijan's New Christmas Skin for Free | Arena of Valor",
      "source": "youtube",
      "publishedAt": "2025-12-12T13:15:09Z"
    },
    {
      "videoId": "fRqTMj6rJds",
      "title": "Veres-S Dreamer skin spotlight",
      "source": "youtube",
      "publishedAt": "2022-11-02T06:38:16Z"
    },
    {
      "videoId": "jhk5Mb8xpcE",
      "title": "Allain-Wolfling Volant skin spotlight",
      "source": "youtube",
      "publishedAt": "2022-11-02T06:38:01Z"
    },
    {
      "videoId": "Km7e-Tokd7c",
      "title": "Alice-Astro Odyssey skin spotlight",
      "source": "youtube",
      "publishedAt": "2022-11-02T06:31:50Z"
    },
    {
      "videoId": "sLQnN8nNdbA",
      "title": "Caphney-Wedding Day skin spotlight",
      "source": "youtube",
      "publishedAt": "2022-11-02T06:29:55Z"
    },
    {
      "videoId": "2cuhh-pZxzw",
      "title": "Xeniel-Demonic Creation skin spotlight",
      "source": "youtube",
      "publishedAt": "2022-08-24T02:49:58Z"
    },
    {
      "videoId": "txaYWe7I3TI",
      "title": "Krixi Sakura Ukiyoe Skin Spotlight - Garena AOV Indonesia #arenaofvalor",
      "source": "youtube",
      "publishedAt": "2026-03-12T12:01:37Z"
    },
    {
      "videoId": "uaBYtbVqDjA",
      "title": "Ringmaster Ishar Skin Spotlight - Garena AOV Indonesia #arenaofvalor #codexs86",
      "source": "youtube",
      "publishedAt": "2026-03-02T10:01:22Z"
    },
    {
      "videoId": "DfmkIkWE5-8",
      "title": "Zip Ringmaster Skin Spotlight - Garena AOV Indonesia #arenaofvalor #codexs86",
      "source": "youtube",
      "publishedAt": "2026-03-02T08:37:38Z"
    },
    {
      "videoId": "cJpL08gjutM",
      "title": "Marja Xi Fei Skin Spotlight - Garena AOV Indonesia #arenaofvalor",
      "source": "youtube",
      "publishedAt": "2026-02-27T07:07:13Z"
    },
    {
      "videoId": "L_-HN6BtdHk",
      "title": "Butterfly Gentle Blade Skin Spotlight - Garena AOV Indonesia",
      "source": "youtube",
      "publishedAt": "2026-02-25T12:00:40Z"
    },
    {
      "videoId": "BcPOMmusWS4",
      "title": "Murad Fortune Bringer Evil Purger Skin Spotlight - Garena AOV Indonesia #arenaofvalor",
      "source": "youtube",
      "publishedAt": "2026-02-05T10:00:18Z"
    },
    {
      "videoId": "y4SyyPdyAWQ",
      "title": "Yue Chaos Sovereign Skin Spotlight - Garena AOV Indonesia #arenaofvalor",
      "source": "youtube",
      "publishedAt": "2026-01-28T07:32:33Z"
    },
    {
      "videoId": "MzEFbVto5gc",
      "title": "Cinnamoroll's Dream Aya Skin Spotlight - Garena AOV Indonesia #Sanriocharacters #arenaofvalor",
      "source": "youtube",
      "publishedAt": "2026-01-01T03:09:05Z"
    },
    {
      "videoId": "olqkhmaSjuo",
      "title": "Chaugnar Pixel Storm Skin Spotlight - Garena AOV Indonesia #arenaofvalor #codexs84",
      "source": "youtube",
      "publishedAt": "2025-12-31T07:53:00Z"
    },
    {
      "videoId": "T_5hNV8-W8A",
      "title": "AOV Masters × Dev Team – 10th Anniversary Special Edition #arenaofvalor",
      "source": "youtube",
      "publishedAt": "2025-12-31T02:38:41Z"
    },
    {
      "videoId": "qetyoUnsbZw",
      "title": "Cinnamoroll's Dream Aya - Garena AOV Indonesia",
      "source": "youtube",
      "publishedAt": "2025-12-29T10:01:40Z"
    },
    {
      "videoId": "8Ka5laFgS4Q",
      "title": "Kuromi's Heart Natalya - Garena AOV Indonesia #Sanriocharacters #arenaofvalor",
      "source": "youtube",
      "publishedAt": "2025-12-29T03:35:30Z"
    },
    {
      "videoId": "7sAyHkOgmRY",
      "title": "My Melody's Love Veera Skin Spotlight - Garena AOV Indonesia #Sanriocharacters #arenaofvalor",
      "source": "youtube",
      "publishedAt": "2025-12-23T10:00:12Z"
    },
    {
      "videoId": "_jAAvaTEChU",
      "title": "Grand Finals AOV Mendadak Tourney 2025 - Garena AOV Indonesia!",
      "source": "youtube",
      "publishedAt": "2025-12-21T13:42:46Z"
    },
    {
      "videoId": "ypWBHi90fpk",
      "title": "Lin Qun | Cch Nhn FREE Rng Skin V Qu Ton Sever S Kin Mi 8/3 Nha",
      "source": "youtube",
      "publishedAt": "2026-03-07T04:24:23Z"
    },
    {
      "videoId": "3hZjtMQxiRQ",
      "title": "Lin Qun | Cch Nhn 2 Skin V Giy V Ba Tuyt Sc Min Ph Ton Sever S Kin Chn Hon Truyn",
      "source": "youtube",
      "publishedAt": "2026-02-28T04:57:16Z"
    },
    {
      "videoId": "5dYwJhiL6RA",
      "title": "Lin Qun | Nhp CODE Nhn Giy V Ba Tuyt Sc V Skin Hp Tc Min Ph Ton Sever Cc Xn",
      "source": "youtube",
      "publishedAt": "2026-02-27T04:30:06Z"
    },
    {
      "videoId": "HH2bEfabRMc",
      "title": "Lin Qun | Cch Nhn Skin SSS V Qun Huy Min Ph X L X Nhn Qu Mng 1 Tt 2026 Nha",
      "source": "youtube",
      "publishedAt": "2026-02-17T05:19:53Z"
    },
    {
      "videoId": "OmCwHNQvSCM",
      "title": "Lin Qun | Cch Nhn Full im Chung Sc M Vn Nhn Qu Rng Skin SS Min Ph Ton Sever Nha",
      "source": "youtube",
      "publishedAt": "2026-02-12T07:00:55Z"
    },
    {
      "videoId": "Yp1mLhfGtto",
      "title": "Lin Qun | Cch Nhn FREE Full Qu Rng Skin V Qun Huy Min Ph V S Kin Chung Sc Tt 2026",
      "source": "youtube",
      "publishedAt": "2026-02-11T04:20:58Z"
    },
    {
      "videoId": "QA3uAEZNeYU",
      "title": "Lin Qun | Cch Nhn FREE Rng Skin SS Trong S Kin Chung Sc M Vn Tt 2026 Nha",
      "source": "youtube",
      "publishedAt": "2026-02-07T04:24:30Z"
    },
    {
      "videoId": "Y-JKqqD2S5Q",
      "title": "Lin Qun | Cch Nhn FREE Skin SSS Qu Qun Huy M Bao L X Khai Vn S Kin Siu S Khai Xun",
      "source": "youtube",
      "publishedAt": "2026-02-05T05:05:00Z"
    },
    {
      "videoId": "cVjRDLINsoM",
      "title": "Lin Qun | 2 S Kin Mi Nhn FREE Skin V Qun Huy Min Ph - Siu X Khai Xun V Quay Tr Li",
      "source": "youtube",
      "publishedAt": "2026-02-03T05:13:40Z"
    },
    {
      "videoId": "GZ1AtandN-Q",
      "title": "VUX LEO RANK CHIẾN TƯỚNG VỚI SKIN KRIXI KIMONO COMBO HOA ANH ĐÀO CỰC ĐẸP",
      "source": "youtube",
      "publishedAt": "2026-03-14T09:49:59Z"
    },
    {
      "videoId": "c2MFzdrdD8s",
      "title": "VUX THỬ THÁCH CHƠI TẤT CẢ SKIN TẾT 2026 LEO NICK HƠN 6000 TRẬN LÊN CHIẾN TƯỚNG CỰC CĂNG",
      "source": "youtube",
      "publishedAt": "2026-03-13T09:05:17Z"
    },
    {
      "videoId": "0p9wH3QBw28",
      "title": "VUX LEO RANK LN CAO TH VI TT C SKIN ILUMIA HOA HU LIN QUN MOBILE",
      "source": "youtube",
      "publishedAt": "2026-03-05T09:46:54Z"
    },
    {
      "videoId": "xXJD_YJwxSc",
      "title": "VUX MT NGY LEO RANK VI BIT I SSM 87 RP XIC K O LIN QUN MOBILE",
      "source": "youtube",
      "publishedAt": "2026-03-03T09:53:26Z"
    },
    {
      "videoId": "f8M10WkkUtc",
      "title": "VUX LEO RANK VI SKIN MI MARJA HI PHI CHN HON TRUYN TRONG LIN QUN MOBILE",
      "source": "youtube",
      "publishedAt": "2026-02-27T10:23:13Z"
    },
    {
      "videoId": "4i17hDSWD94",
      "title": "VUX HÀNH TRÌNH LEO CHIẾN TƯỚNG RANDOM SKIN ANIME ĐẦY KHÓ KHĂN",
      "source": "youtube",
      "publishedAt": "2026-02-26T10:09:49Z"
    },
    {
      "videoId": "Q_-2DOUSHBw",
      "title": "VUX MỘT ĐÊM ĐẤU ĐỈNH CAO TẤT CẢ SKIN TAARA LEO TOP 20 VIỆT NAM ĐẦY CĂNG THẲNG",
      "source": "youtube",
      "publishedAt": "2026-02-25T09:35:21Z"
    },
    {
      "videoId": "x7oz9D7aCY4",
      "title": "VUX LẦN ĐẦU CHẠM NICK TOP 1 TRANG PHỤC THẾ GIỚI VÀ TEST TƯỚNG MỚI DYADIA TRỢ THỦ CƯỚP VÀNG",
      "source": "youtube",
      "publishedAt": "2026-02-24T09:56:22Z"
    },
    {
      "videoId": "EB9QoRcWFf8",
      "title": "Vị Tướng Out Meta Này Đang Làm Trùm Xạ Thủ ?",
      "source": "youtube",
      "publishedAt": "2026-03-12T11:15:00Z"
    },
    {
      "videoId": "GQ31QZGV4eg",
      "title": "Tại Sao Các Tướng DC Hiện Tại Toàn Phế Vật ?",
      "source": "youtube",
      "publishedAt": "2026-03-05T11:00:00Z"
    },
    {
      "videoId": "vQLa0nzSjWw",
      "title": "Marja Hi Phi Là Một Skin Tệ Hại ?",
      "source": "youtube",
      "publishedAt": "2026-03-03T11:00:00Z"
    },
    {
      "videoId": "DLotLwi2gkY",
      "title": "Vị Tướng Out Meta Này Là Kẻ Hủy Diệt Xạ Thủ ?",
      "source": "youtube",
      "publishedAt": "2026-02-25T11:00:00Z"
    },
    {
      "videoId": "rCVBC4HBRsA",
      "title": "[icyfoxx] Chi v nh gi tt c skin Tt 2026 nh lm - 4 b th 3 b b ch ti t | Lin qun",
      "source": "youtube",
      "publishedAt": "2026-03-04T05:55:40Z"
    },
    {
      "videoId": "-FODcQHz5Xw",
      "title": "Ti Enzo th sc cng tr chi \" CUN \" hn c leo rank Lin Qun",
      "source": "youtube",
      "publishedAt": "2026-03-06T11:00:01Z"
    },
    {
      "videoId": "-VS0nTQupE4",
      "title": "Tập 3 - Thần Tài Enzo phát thẻ giảm giá và hành trình lên Chiến Tướng dễ không tưởng",
      "source": "youtube",
      "publishedAt": "2026-02-17T10:12:56Z"
    },
    {
      "videoId": "dqJaQc4yUhs",
      "title": "Tp 2 - Cch c th gim gi 799 Qun Huy cc d khi leo rank cng Ti Enzo",
      "source": "youtube",
      "publishedAt": "2026-02-15T11:01:02Z"
    }
  ]
}