{
  "videos": [
    {
      "videoId": "44-Hwn50IQ4",
      "title": "Arduin Meta Mới: Buff Xong Đánh Cực Láo!",
      "source": "youtube",
      "publishedAt": "2026-04-03T09:30:05Z"
    },
    {
      "videoId": "dpd1GxAWskE",
      "title": "Lin Qun Top 5 Tng Khc Ch Enzo, Hot Pick Gii v Rank 2026, TNG",
      "source": "youtube",
      "publishedAt": "2026-04-03T03:05:10Z"
    },
    {
      "videoId": "lHtsPKkqK6w",
      "title": "Thoát Flop, Astrid Sửa Vòng Trở Lại Meta Mới ?",
      "source": "youtube",
      "publishedAt": "2026-04-02T09:30:21Z"
    },
    {
      "videoId": "NxGSLs2Y79c",
      "title": "Lin Qun Top 5 Tng Khc Ch Volkath, Hot Meta Ma S1 2026, TNG",
      "source": "youtube",
      "publishedAt": "2026-04-01T03:11:11Z"
    },
    {
      "videoId": "FEhGCtxc21M",
      "title": "Lin Qun Top 5 Tng Khc Ch Ryoma, Buff Xong Hot Rank Ma S1 2026, TNG",
      "source": "youtube",
      "publishedAt": "2026-03-30T03:00:00Z"
    }
  ]
}